Workbook

Sheet Содержание
A1: ToolKit Финансы. Блок Финансовое моделирование. Содержание практики
B3: Changellenge >> ToolKit.
B5: Оценка бизнеса и проектов методом DCF. Домашнее задание 4
B6: Файл для самостоятельной работы
B8: № | C8: Лист | D8: Содержимое / описание | E8: Действие
B9: 1 | C9: Введение | D9: Описание кейса и задания | E9: Изучить
B10: 2 | C10: Assumptions & Inputs | D10: Структурированные вводные данные для расчетов в модели | E10: Заполнить на основе листа "Данные"
B11: 3 | C11: Прогнозы | D11: Прогноз продаж и производства | E11: Заполнить и получить ответ
B12: 4 | C12: Себестоимость | D12: Расчет себестоимости методом ABC и цены методом кост-плюс | E12: Заполнить и получить ответ
B13: 5 | C13: CF | D13: Отчет о движении денежных средств | E13: Заполнить и получить ответ
B14: 6 | C14: P&L | D14: Отчет о прибылях и убытках | E14: Заполнить и получить ответ
B15: 7 | C15: Показатели | D15: Расчет периода окупаемости, IRR и NPV проекта | E15: Заполнить и получить ответ
B16: 8 | C16: Данные | D16: Вводные данные от аналитиков, инициаторв проекта и производственного отдела | E16: Изучить
B18: ОБРАТИТЕ ВНИМАНИЕ!
B19: Это файл для самостоятельной работы. Используйте для решения задания только данные, которые содержатся в этом файле. В каждом новом домашнем задании вам будут открываться заполненные листы с практики прошлого блока + новые чистые листы для решения текущего задания

Sheet Comments
C3: Address | D3: Comment | E3: Worksheet | H3: LS | M3: PG
C4: {='Assumptions and inputs'!$H$105} -> 0.33333333 | D4: Этот показатель нужен для расчета releverd beta. В WACC нужно взвешивать доходности по долям компонентов в структуре капитала | E4: Assumptions and inputs | H4: так, то есть не правильно? Я думала это так и получается в расчете беты его задействовала) | M4: Не правильно) Надо брать D / (D + E) и, соответственно, E / (D + E)
C5: {='Assumptions and inputs'!$H$7:$H$19} -> 0 | D5: Вот эти прочерки ставить не нужно. На них ломаются формулы | E5: Assumptions and inputs | H5: убрала везде
C6: {='Assumptions and inputs'!$K$19:$L$19} -> 1.0040182 | D6: Лучше избегать таких формул. Можно через IF делать | E6: Assumptions and inputs | H6: это ошибка? Если нет, то давай оставим или ты можешь в видео сказать об этом (почему так лучше не делать) и перестроить | I6: Там же обычное умножение стоит(( | M6: Формула в строке не должна меняться. Если тебе нужно взять из базы значение в первом периоде, то ты ифом проверяешь, что период первый и берешь из базы, иначе предыдущий
C7: {='Assumptions and inputs'!$N$79:$N$81} -> 0 | D7: Непонятные харды посреди прогноза | E7: Assumptions and inputs | H7: готово
C8: {=Прогнозы!$K$26} -> 5000000 | D8: Тут не нужна формула массива. Годы и % есть в строке 12, ссылка на Assumptions не нужна | E8: Прогнозы | H8: ее же там нет Там Index(Match()) стоит | M8: У меня в прошлой версии формула была в фигурных скобках
C9: {=Прогнозы!$D$26:$D$28} -> Плановый годовой объем производства | D9: Не сразу понятно, чем отличаются данные показатели. Переименовать | E9: Прогнозы | H9: сделала проще
C10: {=Прогнозы!$K$25:$N$25} -> 0 | D10: Не понимаю смысл этого расчета (тем более харды в формулах, которых быть не должно). Логика простая: плановый годовой объем производства -> плановый объем производства в период через простое умножение на длину периода -> плановый объем производства в период с учетом домножения на коэффициент сезонности. Все )) Если таким образом делается учет того, что в первом неполном году нужно продать ровно 5 млн единиц запланированных, то проще и лучше скорректировать инпуты. Так они будут consistent: годовой объем производства, который уже далее корректируется с учетом временной шкалы | E10: Прогнозы
C11: {=Прогнозы!$K$28} -> 318493.15 | D11: Формула массива не нужна | E11: Прогнозы | H11: ее же там нет Там Index(Match()) стоит обычный
C12: {=Себестоимость!$I$77} -> 0 | D12: Обрати внимание, что рентабельность получается не 60% | E12: Себестоимость | H12: а почему(( как правильно? | M12: Поправил
C13: {=CF!$D$29} -> Cвободный денежный поток на фирму (FCFF) | D13: Более общепринятое название "на фирму" | E13: CF
C14: {=CF!$D$70} -> Свободный денежный поток на акционерный капитал (FCFE) | D14: А здесь "на акционерный капитал" | E14: CF
C15: {=CF!$K$20} -> 138.32 | D15: Не нужна формула массива | E15: CF | H15: Тут убрали. Теперь прсото Index (Match())
C16: {=CF!$K$21} -> 138.32 | D16: Инфляция считается неправильно. Если строка 17 - в реальных ценах на дату анализа, то строка 18 должна корректироваться на куммулятивный индекс с даты анализа по период прогноза | E16: CF | H16: не понимаю( | M16: Поправил
C17: {=CF!$K$34:$K$36} -> 0 | D17: Лучше все расходы сразу пускать с минусом. Так точно никто не запутается и не наделает ошибок | E17: CF | H17: если не критично, давай так оставим. Если будет время переделаю быстренько
C18: {=CF!$D$29} -> Cвободный денежный поток на фирму (FCFF) | D18: Можешь посмотреть, как структурирована эта история в моей модели по девелопменту (Lite), которую отправлял по итогам кейс стади в четверг | E18: CF
C19: {=CF!#REF!} -> #REF! | D19: НДС есть на этом листе | E19: CF | H19: можешь помочь?
C20: {=CF!$K$37} -> 0 | D20: Переписал формулу, посмотри | E20: CF
C21: {=CF!$K$38:$K$46} -> 0 | D21: С НДС явно что-то не то. Потоков по НДС так и не возникает | E21: CF | H21: можешь помочь?
C22: {=CF!$K$39:$K$46} -> 0 | D22: Где НДС по инвестиционной деятельности? | E22: CF | H22: можешь помочь? | M22: Появился
C23: {=CF!$K$49:$K$57} -> 152500000 | D23: Тотали отформатировать, минусы добавить | E23: CF
C24: {=CF!$M$78} -> 7576544.1 | D24: Привлекаем и сразу гасим тело? На какие деньги? | E24: CF | H24: можешь помочь? | M24: Поправил
C25: {=CF!$L$79} -> 0 | D25: Проценты вынести в фикс знач | E25: CF | H25: готово
C26: {=CF!$N$79} -> 1253701.7 | D26: Проценты нигде не учитываются | E26: CF | H26: куда их правильно поместить? в расходы операц деятельности?
C27: {=CF!$N$79} -> 1253701.7 | D27: Отнести в операционную деятельность | E27: CF | H27: готово, в 84 ячейке
C28: {=CF!$K$102:$AT$102} -> 0 | D28: Сумма не равна нулю | E28: CF | H28: можешь помочь?
C29: {=CF!$H$106} -> 4.3057677e+08 | D29: Сумма по FCFE не может быть больше суммы FCFF. | E29: CF | H29: можешь помочь?
C30: {='P&L'!$K$29} -> 0 | D30: Себестоимость должна признаваться при продажах | E30: P&L | H30: в ПЛ сделала себест*график продаж, правильно?
C31: {=CF!$K$34} -> 0 | D31: Себестоимость должна признаваться при продаже | E31: CF | H31: в СФ тоже? Я думала нет( | M31: Все верно посчитано здесь, я промахнулся, имел в виду блок ниже )
C32: {=CF!$H$36} -> 0.1 | D32: Админ расходов на стадии производства нет?) | E32: CF | H32: нет))
C33: {='P&L'!$G$37} -> 0 | D33: Добавить проверку, что налог на прибыль равен тому, что уплачивается на CF | E33: P&L | H33: можешь помочь?
C34: {=CF!$K$37} -> 0 | D34: Лучше всего его рассчитать на листе PnL | E34: CF | H34: а почему тогда СФ первым считается, я сперва поэтому ПЛ и построила первым :D | M34: Здесь получается логика "туда-обратно". Сначала считается СФ, от него считается признание для ПнЛ, там считается налог на прибыль, и он возвращается в ПнЛ. И уже на этом базисе считается колесо финансирования и тд
H35: еще не перенесла

Sheet Введение
A1: ToolKit Финансы. Блок Финансовое моделирование. Введение в практический блок
B4: Описание кейса
B6: Вы работаете в стратегическом департаменте компании "Маруся" - крупнейшей российской FMCG компании. Год назад компания начала производство овсяного и соевого молока. Продукты стали успешными на рынке, в связи с чем, в компании решили запустить другие, более дорогие виды растительного молока.
B8: В этом году компания планирует запустить производство кокосового молока.
B10: Ваша задача - оценить этот проект.
B12: Для этого вам нужно:
B13: 1 | C13: Подготовить исходные данные для модели
B14: 2 | C14: Составить отчет о движении денежных средств
B15: 3 | C15: Составить отчет о прибялях и убытках
B16: 4 | C16: Рассчитать показатели, необходимые для оценки проекта.
B19: Модель должна быть построена на 3 года с разбивкой по месяцам
B24: Алгоритм работы
B26: Шаг 0 | C26: Подготовьте структуру модели
B28: Шаг 1 | C28: Изучите вводные данные
B30: Шаг 2 | C30: Заполните лист Assumptions & Inputs
B32: Шаг 3 | C32: Постройте прогноз производства и прогноз продаж
B34: Шаг 4 | C34: Рассчитайте себестоимость продукта методом АБС и определите цену методом кост-плюс
B36: Шаг 5 | C36: Постройте CF
B38: Шаг 6 | C38: Постройте PL
B40: Шаг 7 | C40: Рассчитайте показатели проекта

Sheet Assumptions and inputs
D1: ToolKit Финансы. Блок Финансовое моделирование. Assumptions and inputs
D3: Шаг 1. Постройте единую для всей модели временную шкалу
C5: Временные шкалы
E6: Ед.изм. | F6: Комментарий | G6: Проверка | H6: Фикс.значения * | I6: База * | K6: =YEAR(K7) -> 2029 | L6: =YEAR(L7) -> 2029 | M6: =YEAR(M7) -> 2029 | N6: =YEAR(N7) -> 2029 | O6: =YEAR(O7) -> 2029 | P6: =YEAR(P7) -> 2029 | Q6: =YEAR(Q7) -> 2029 | R6: =YEAR(R7) -> 2029 | ... AT6: =YEAR(AT7) -> 2031
D7: Начало периода | E7: дата | K7: =I8 + 1 -> 47119 | L7: =K8 + 1 -> 47150 | M7: =L8 + 1 -> 47178 | N7: =M8 + 1 -> 47209 | O7: =N8 + 1 -> 47239 | P7: =O8 + 1 -> 47270 | Q7: =P8 + 1 -> 47300 | R7: =Q8 + 1 -> 47331 | S7: =R8 + 1 -> 47362 | ... AT7: =AS8 + 1 -> 48183
D8: Конец периода | E8: дата | F8: =EOMONTH(K7; 0) | I8: 47118 | K8: =EOMONTH(K7, 0) -> 47149 | L8: =EOMONTH(L7, 0) -> 47177 | M8: =EOMONTH(M7, 0) -> 47208 | N8: =EOMONTH(N7, 0) -> 47238 | O8: =EOMONTH(O7, 0) -> 47269 | P8: =EOMONTH(P7, 0) -> 47299 | Q8: =EOMONTH(Q7, 0) -> 47330 | R8: =EOMONTH(R7, 0) -> 47361 | ... AT8: =EOMONTH(AT7, 0) -> 48213
D9: Номер периода | E9: - | F9: От 1 до36 | I9: 0 | K9: =I9 + 1 -> 1 | L9: =K9 + 1 -> 2 | M9: =L9 + 1 -> 3 | N9: =M9 + 1 -> 4 | O9: =N9 + 1 -> 5 | P9: =O9 + 1 -> 6 | Q9: =P9 + 1 -> 7 | R9: =Q9 + 1 -> 8 | S9: =R9 + 1 -> 9 | ... AT9: =AS9 + 1 -> 36
D10: Длина периода | E10: - | F10: Для корректировки годовых значений в период | K10: =(K8-K7)/365 -> 0.082191781 | L10: =(L8-L7)/365 -> 0.073972603 | M10: =(M8-M7)/365 -> 0.082191781 | N10: =(N8-N7)/365 -> 0.079452055 | O10: =(O8-O7)/365 -> 0.082191781 | P10: =(P8-P7)/365 -> 0.079452055 | Q10: =(Q8-Q7)/365 -> 0.082191781 | R10: =(R8-R7)/365 -> 0.082191781 | ... AT10: =(AT8-AT7)/365 -> 0.082191781
D12: Шаг 2. Задайте макропоказатели
D14: Макроэкономические показатели
D15: Год | E15: - | I15: =YEAR(I8) -> 2028 | K15: =I15 + 1 -> 2029 | L15: =K15 + 1 -> 2030 | M15: =L15 + 1 -> 2031 | N15: =M15 + 1 -> 2032 | O15: =N15 + 1 -> 2033
D16: Среднегодовая инфляция | E16: % | I16: 0.05 | K16: 0.05 | L16: 0.038 | M16: 0.04 | N16: 0.04 | O16: 0.04
D17: Среднегодовая инфляция в период | E17: % | K17: =INDEX($K$16:$O$16,, MATCH(K$6, $K$15:$O$15, 0)) -> 0.05 | L17: =INDEX($K$16:$O$16,, MATCH(L$6, $K$15:$O$15, 0)) -> 0.05 | M17: =INDEX($K$16:$O$16,, MATCH(M$6, $K$15:$O$15, 0)) -> 0.05 | N17: =INDEX($K$16:$O$16,, MATCH(N$6, $K$15:$O$15, 0)) -> 0.05 | O17: =INDEX($K$16:$O$16,, MATCH(O$6, $K$15:$O$15, 0)) -> 0.05 | P17: =INDEX($K$16:$O$16,, MATCH(P$6, $K$15:$O$15, 0)) -> 0.05 | Q17: =INDEX($K$16:$O$16,, MATCH(Q$6, $K$15:$O$15, 0)) -> 0.05 | R17: =INDEX($K$16:$O$16,, MATCH(R$6, $K$15:$O$15, 0)) -> 0.05 | ... AT17: =INDEX($K$16:$O$16,, MATCH(AT$6, $K$15:$O$15, 0)) -> 0.04
D18: Среднегодовая инфляция за период | E18: % | F18: Инфляция за месяц | K18: =(1 + K17) ^ K10 - 1 -> 0.0040182019 | L18: =(1 + L17) ^ L10 - 1 -> 0.0036156562 | M18: =(1 + M17) ^ M10 - 1 -> 0.0040182019 | N18: =(1 + N17) ^ N10 - 1 -> 0.0038840021 | O18: =(1 + O17) ^ O10 - 1 -> 0.0040182019 | P18: =(1 + P17) ^ P10 - 1 -> 0.0038840021 | Q18: =(1 + Q17) ^ Q10 - 1 -> 0.0040182019 | R18: =(1 + R17) ^ R10 - 1 -> 0.0040182019 | ... AT18: =(1 + AT17) ^ AT10 - 1 -> 0.0032288217
D19: Кумулятивная инфляция | E19: % | I19: 1 | K19: =I19 * (1 + K18) -> 1.0040182 | L19: =K19 * (1 + L18) -> 1.0076484 | M19: =L19 * (1 + M18) -> 1.0116973 | N19: =M19 * (1 + N18) -> 1.0156268 | O19: =N19 * (1 + O18) -> 1.0197077 | P19: =O19 * (1 + P18) -> 1.0236683 | Q19: =P19 * (1 + Q18) -> 1.0277816 | R19: =Q19 * (1 + R18) -> 1.0319114 | S19: =R19 * (1 + S18) -> 1.0359194 | ... AT19: =AS19 * (1 + AT18) -> 1.128836
D21: Налог на прибыль | E21: % | H21: 0.2
D22: НДС | E22: % | H22: 0.2
D24: Шаг 3. Перенесите в модель все необходимые вводные для построения денежных потоков
D26: Вводные для прогноза производства и продаж
D27: Год | E27: - | I27: =YEAR($I$8) -> 2028 | K27: =I27 + 1 -> 2029 | L27: =K27 + 1 -> 2030 | M27: =L27 + 1 -> 2031 | N27: =M27 + 1 -> 2032 | O27: =N27 + 1 -> 2033
D28: Плановый темп роста в год | E28: % | I28: 0 | K28: =I28 -> 0 | L28: 1.15 | M28: 0.2 | N28: 0.2 | O28: 0.2
D29: Плановый объем производства в год запуска проекта | E29: кг | I29: 5000000
D31: Месяц | E31: - | K31: =MONTH(K7) -> 1 | L31: =MONTH(L7) -> 2 | M31: =MONTH(M7) -> 3 | N31: =MONTH(N7) -> 4 | O31: =MONTH(O7) -> 5 | P31: =MONTH(P7) -> 6 | Q31: =MONTH(Q7) -> 7 | R31: =MONTH(R7) -> 8 | ... V31: =MONTH(V7) -> 12
D32: Сезонность | E32: - | K32: 0.75 | L32: 0.85 | M32: 0.9 | N32: 1.1 | O32: 1.2 | P32: 1.25 | Q32: 1.2 | R32: 1.1 | S32: 1.05 | T32: 0.95 | U32: 0.85 | V32: 0.8
D34: Месяц начала продаж | E34: мес | H34: 3
D35: Период между производством и продажей | E35: мес | H35: 1
D37: Вводные для расчета себестоимости и цены
D38: Партия производства | E38: кг | H38: 120
D39: Число переналадок оборудования за партию | E39: - | H39: 5
D40: Партия продажи | E40: кг | H40: 95
D41: Рентабельность аналогичных продуктов в компании | E41: % | H41: 0.45
D43: Состав продукта и стоимость сырья
D44: Стоимость сырья
D45: Кокосовая паста | E45: руб/кг | I45: 380
D46: Карбонат кальция | E46: руб/кг | I46: 75
D47: Витамины | E47: руб/кг | I47: 4500
D48: Камедь рожкового дерева | E48: руб/кг | I48: 1500
D49: Лецитин подсолнечный | E49: руб/кг | I49: 234
D50: Состав 1 кг продукта
D51: Основа - кокосовая паста | E51: кг | I51: 0.17
D52: Кальций | E52: кг | I52: 0.01
D53: Витамины | E53: кг | I53: 0.007
D54: Стабилизатор (камедь рожкового дерева) | E54: кг | I54: 0.008
D55: Эмульгатор (лецитин подсолнечный) | E55: кг | I55: 0.005
D56: Вода | E56: кг | I56: 0.8
D58: Прочие прямые расходы
D59: Заработная плата производственным рабочим | E59: руб | F59: На изготовление 1кг продукта | I59: 20
D60: Прочие прямые затраты | E60: руб | F60: На изготовление 1кг продукта | I60: 5
D62: Накладные расходы за год
D63: Общие затраты по управлению цехом | E63: руб | I63: 4500000
D64: Затраты на наладку оборудования | E64: руб | I64: 4000000
D65: Административные расходы | E65: руб | I65: 8000000
D67: Инвестиции проекта
D68: =D77 -> Процессное оборудование
D69: =D78 -> Приемка сырья | E69: % | G69: =SUM(K69:AU69) -> 1 | H69: 1 | K69: 0.5 | L69: 0.5 | M69: 0 | N69: 0 | O69: 0 | P69: 0 | Q69: 0 | R69: 0 | S69: 0 | T69: 0 | U69: 0 | V69: 0 | W69: 0 | X69: 0 | Y69: 0 | Z69: 0 | AA69: 0 | AB69: 0 | AC69: 0 | AD69: 0 | AE69: 0 | AF69: 0 | AG69: 0 | AH69: 0 | AI69: 0 | AJ69: 0 | AK69: 0 | AL69: 0 | AM69: 0 | AN69: 0 | AO69: 0 | AP69: 0 | AQ69: 0 | AR69: 0 | AS69: 0 | AT69: 0
D70: =D79 -> Миксинг | E70: % | G70: =SUM(K70:AU70) -> 1 | H70: 1 | K70: 0.5 | L70: 0.5 | M70: 0 | N70: 0 | O70: 0 | P70: 0 | Q70: 0 | R70: 0 | S70: 0 | T70: 0 | U70: 0 | V70: 0 | W70: 0 | X70: 0 | Y70: 0 | Z70: 0 | AA70: 0 | AB70: 0 | AC70: 0 | AD70: 0 | AE70: 0 | AF70: 0 | AG70: 0 | AH70: 0 | AI70: 0 | AJ70: 0 | AK70: 0 | AL70: 0 | AM70: 0 | AN70: 0 | AO70: 0 | AP70: 0 | AQ70: 0 | AR70: 0 | AS70: 0 | AT70: 0
D71: =D80 -> Декантация и деактивация | E71: % | G71: =SUM(K71:AU71) -> 1 | H71: 1 | K71: 0.5 | L71: 0.5 | M71: 0 | N71: 0 | O71: 0 | P71: 0 | Q71: 0 | R71: 0 | S71: 0 | T71: 0 | U71: 0 | V71: 0 | W71: 0 | X71: 0 | Y71: 0 | Z71: 0 | AA71: 0 | AB71: 0 | AC71: 0 | AD71: 0 | AE71: 0 | AF71: 0 | AG71: 0 | AH71: 0 | AI71: 0 | AJ71: 0 | AK71: 0 | AL71: 0 | AM71: 0 | AN71: 0 | AO71: 0 | AP71: 0 | AQ71: 0 | AR71: 0 | AS71: 0 | AT71: 0
D72: =D81 -> Гомогенизация и стерилизация | E72: % | G72: =SUM(K72:AU72) -> 1 | H72: 1 | K72: 0.5 | L72: 0.5 | M72: 0 | N72: 0 | O72: 0 | P72: 0 | Q72: 0 | R72: 0 | S72: 0 | T72: 0 | U72: 0 | V72: 0 | W72: 0 | X72: 0 | Y72: 0 | Z72: 0 | AA72: 0 | AB72: 0 | AC72: 0 | AD72: 0 | AE72: 0 | AF72: 0 | AG72: 0 | AH72: 0 | AI72: 0 | AJ72: 0 | AK72: 0 | AL72: 0 | AM72: 0 | AN72: 0 | AO72: 0 | AP72: 0 | AQ72: 0 | AR72: 0 | AS72: 0 | AT72: 0
D73: =D82 -> Упаковочная линия
D74: =D83 -> Фасовка | E74: % | G74: =SUM(K74:AU74) -> 1 | H74: 1 | K74: 0.5 | L74: 0.5 | M74: 0 | N74: 0 | O74: 0 | P74: 0 | Q74: 0 | R74: 0 | S74: 0 | T74: 0 | U74: 0 | V74: 0 | W74: 0 | X74: 0 | Y74: 0 | Z74: 0 | AA74: 0 | AB74: 0 | AC74: 0 | AD74: 0 | AE74: 0 | AF74: 0 | AG74: 0 | AH74: 0 | AI74: 0 | AJ74: 0 | AK74: 0 | AL74: 0 | AM74: 0 | AN74: 0 | AO74: 0 | AP74: 0 | AQ74: 0 | AR74: 0 | AS74: 0 | AT74: 0
D75: =D84 -> Группировка | E75: % | G75: =SUM(K75:AU75) -> 1 | H75: 1 | K75: 0.5 | L75: 0.5 | M75: 0 | N75: 0 | O75: 0 | P75: 0 | Q75: 0 | R75: 0 | S75: 0 | T75: 0 | U75: 0 | V75: 0 | W75: 0 | X75: 0 | Y75: 0 | Z75: 0 | AA75: 0 | AB75: 0 | AC75: 0 | AD75: 0 | AE75: 0 | AF75: 0 | AG75: 0 | AH75: 0 | AI75: 0 | AJ75: 0 | AK75: 0 | AL75: 0 | AM75: 0 | AN75: 0 | AO75: 0 | AP75: 0 | AQ75: 0 | AR75: 0 | AS75: 0 | AT75: 0
D76: =D85 -> Работа над технологией | E76: % | G76: =SUM(K76:AU76) -> 1 | H76: 1 | K76: 0.5 | L76: 0.5 | M76: 0 | N76: 0 | O76: 0 | P76: 0 | Q76: 0 | R76: 0 | S76: 0 | T76: 0 | U76: 0 | V76: 0 | W76: 0 | X76: 0 | Y76: 0 | Z76: 0 | AA76: 0 | AB76: 0 | AC76: 0 | AD76: 0 | AE76: 0 | AF76: 0 | AG76: 0 | AH76: 0 | AI76: 0 | AJ76: 0 | AK76: 0 | AL76: 0 | AM76: 0 | AN76: 0 | AO76: 0 | AP76: 0 | AQ76: 0 | AR76: 0 | AS76: 0 | AT76: 0
D77: Процессное оборудование
D78: Приемка сырья | E78: руб. | G78: =SUM(K78:AU78) -> 90000000 | H78: 90000000 | K78: =K69*$H78 -> 45000000 | L78: =L69*$H78 -> 45000000 | M78: =M69*$H78 -> 0 | N78: =N69*$H78 -> 0 | O78: =O69*$H78 -> 0 | P78: =P69*$H78 -> 0 | Q78: =Q69*$H78 -> 0 | R78: =R69*$H78 -> 0 | ... AT78: =AT69*$H78 -> 0
D79: Миксинг | E79: руб. | G79: =SUM(K79:AU79) -> 70000000 | H79: 70000000 | K79: =K70*$H79 -> 35000000 | L79: =L70*$H79 -> 35000000 | M79: =M70*$H79 -> 0 | N79: =N70*$H79 -> 0 | O79: =O70*$H79 -> 0 | P79: =P70*$H79 -> 0 | Q79: =Q70*$H79 -> 0 | R79: =R70*$H79 -> 0 | ... AT79: =AT70*$H79 -> 0
D80: Декантация и деактивация | E80: руб. | G80: =SUM(K80:AU80) -> 55000000 | H80: 55000000 | K80: =K71*$H80 -> 27500000 | L80: =L71*$H80 -> 27500000 | M80: =M71*$H80 -> 0 | N80: =N71*$H80 -> 0 | O80: =O71*$H80 -> 0 | P80: =P71*$H80 -> 0 | Q80: =Q71*$H80 -> 0 | R80: =R71*$H80 -> 0 | ... AT80: =AT71*$H80 -> 0
D81: Гомогенизация и стерилизация | E81: руб. | G81: =SUM(K81:AU81) -> 90000000 | H81: 90000000 | K81: =K72*$H81 -> 45000000 | L81: =L72*$H81 -> 45000000 | M81: =M72*$H81 -> 0 | N81: =N72*$H81 -> 0 | O81: =O72*$H81 -> 0 | P81: =P72*$H81 -> 0 | Q81: =Q72*$H81 -> 0 | R81: =R72*$H81 -> 0 | ... AT81: =AT72*$H81 -> 0
D82: Упаковочная линия
D83: Фасовка | E83: руб. | G83: =SUM(K83:AU83) -> 70000000 | H83: 70000000 | K83: =K74*$H83 -> 35000000 | L83: =L74*$H83 -> 35000000 | M83: =M74*$H83 -> 0 | N83: =N74*$H83 -> 0 | O83: =O74*$H83 -> 0 | P83: =P74*$H83 -> 0 | Q83: =Q74*$H83 -> 0 | R83: =R74*$H83 -> 0 | ... AT83: =AT74*$H83 -> 0
D84: Группировка | E84: руб. | G84: =SUM(K84:AU84) -> 40000000 | H84: 40000000 | K84: =K75*$H84 -> 20000000 | L84: =L75*$H84 -> 20000000 | M84: =M75*$H84 -> 0 | N84: =N75*$H84 -> 0 | O84: =O75*$H84 -> 0 | P84: =P75*$H84 -> 0 | Q84: =Q75*$H84 -> 0 | R84: =R75*$H84 -> 0 | ... AT84: =AT75*$H84 -> 0
D85: Работа над технологией | E85: руб. | G85: =SUM(K85:AU85) -> 180000000 | H85: 180000000 | K85: =K76*$H85 -> 90000000 | L85: =L76*$H85 -> 90000000 | M85: =M76*$H85 -> 0 | N85: =N76*$H85 -> 0 | O85: =O76*$H85 -> 0 | P85: =P76*$H85 -> 0 | Q85: =Q76*$H85 -> 0 | R85: =R76*$H85 -> 0 | ... AT85: =AT76*$H85 -> 0
D87: Операционные затраты
D88: Маркетинг | E88: % | F88: от выручки | H88: 0.15
D89: АУП и непредвиденные затраты | E89: % | F89: от выручки | H89: 0.1
D91: Амортизация
D92: Срок полезного использования | E92: мес | H92: 40
D93: Стоимость оборудования | E93: руб. | F93: Не учитываем работу над технологией | H93: =SUM(H78:H84) -> 415000000
D94: Амортизационные отчисления в месяц | E94: руб. | H94: =H93/H92 -> 10375000 | K94: =IF(K9<=$H$92,$H$94,0) -> 10375000 | L94: =IF(L9<=$H$92,$H$94,0) -> 10375000 | M94: =IF(M9<=$H$92,$H$94,0) -> 10375000 | N94: =IF(N9<=$H$92,$H$94,0) -> 10375000 | O94: =IF(O9<=$H$92,$H$94,0) -> 10375000 | P94: =IF(P9<=$H$92,$H$94,0) -> 10375000 | Q94: =IF(Q9<=$H$92,$H$94,0) -> 10375000 | R94: =IF(R9<=$H$92,$H$94,0) -> 10375000 | ... AT94: =IF(AT9<=$H$92,$H$94,0) -> 10375000
D96: Шаг 4. Рассчитайте ставки дисконта и задайте условия финансирования
D98: Структура капитала
D99: COE | E99: % | F99: Cost of equity / Стоимость собственного капитала | H99: =H100+H103*H101 -> 0.13001309
D100: Безрисковая ставка | E100: % | F100: Значение бескупонной доходности гос.облигаций сроком погашения 10 лет (July 2019), cbr.ru | H100: =Данные!J88 -> 0.075657895
D101: ERP (risk market - risk free) | E101: % | F101: Average ERP (Jan. 2018), Damodaran | H101: 0.0596
D102: Beta | E102: - | F102: Unlevered beta for Food Processing industry (Jan. 2018), Damodaran | H102: 0.72
D103: Beta relevered | F103: βlevered = βunlevered * [1 + ((1 – Ставка налога) * Долг/Капитал)] | H103: =H102*(1+(1-H21)*H105) -> 0.912
D104: WACC | E104: % | F104: Weighted Average Cost of Capital / Средневзвешенная стоимость капитала | H104: =(1-H109)*H99+H109*H108*(1-$H$21) -> 0.11750982
D105: Долг-к-Капиталу (Debt/Equity) | E105: % | H105: =H109/(1-H109) -> 0.33333333
D107: Условия финансирования
D108: Стоимость заемного финансирования | E108: % | H108: 0.1
D109: Объем заемного финансирования | E109: % | H109: 0.25

Sheet Прогнозы
D1: ToolKit Финансы. Блок Финансовое моделирование. Прогнозирование продаж и производства
D3: Временные шкалы
E4: Ед.изм. | F4: Комментарий | G4: Проверка | H4: Фикс.значения * | I4: База * | K4: =YEAR(K5) -> 2029 | L4: =YEAR(L5) -> 2029 | M4: =YEAR(M5) -> 2029 | N4: =YEAR(N5) -> 2029 | O4: =YEAR(O5) -> 2029 | P4: =YEAR(P5) -> 2029 | Q4: =YEAR(Q5) -> 2029 | R4: =YEAR(R5) -> 2029 | ... AT4: =YEAR(AT5) -> 2031
D5: Начало периода | E5: дата | K5: =I6 + 1 -> 47119 | L5: =K6 + 1 -> 47150 | M5: =L6 + 1 -> 47178 | N5: =M6 + 1 -> 47209 | O5: =N6 + 1 -> 47239 | P5: =O6 + 1 -> 47270 | Q5: =P6 + 1 -> 47300 | R5: =Q6 + 1 -> 47331 | S5: =R6 + 1 -> 47362 | ... AT5: =AS6 + 1 -> 48183
D6: Конец периода | E6: дата | I6: ='Assumptions and inputs'!I8 -> 47118 | K6: =EOMONTH(K5, 0) -> 47149 | L6: =EOMONTH(L5, 0) -> 47177 | M6: =EOMONTH(M5, 0) -> 47208 | N6: =EOMONTH(N5, 0) -> 47238 | O6: =EOMONTH(O5, 0) -> 47269 | P6: =EOMONTH(P5, 0) -> 47299 | Q6: =EOMONTH(Q5, 0) -> 47330 | R6: =EOMONTH(R5, 0) -> 47361 | ... AT6: =EOMONTH(AT5, 0) -> 48213
D7: Номер периода | I7: ='Assumptions and inputs'!I9 -> 0 | K7: =I7 + 1 -> 1 | L7: =K7 + 1 -> 2 | M7: =L7 + 1 -> 3 | N7: =M7 + 1 -> 4 | O7: =N7 + 1 -> 5 | P7: =O7 + 1 -> 6 | Q7: =P7 + 1 -> 7 | R7: =Q7 + 1 -> 8 | S7: =R7 + 1 -> 9 | ... AT7: =AS7 + 1 -> 36
D8: Длина периода | K8: =(K6 - K5 + 1) / (DATE(YEAR(K6), 12, 31) - DATE(YEAR(K6), 1, 1) + 1) -> 0.084931507 | L8: =(L6 - L5 + 1) / (DATE(YEAR(L6), 12, 31) - DATE(YEAR(L6), 1, 1) + 1) -> 0.076712329 | M8: =(M6 - M5 + 1) / (DATE(YEAR(M6), 12, 31) - DATE(YEAR(M6), 1, 1) + 1) -> 0.084931507 | N8: =(N6 - N5 + 1) / (DATE(YEAR(N6), 12, 31) - DATE(YEAR(N6), 1, 1) + 1) -> 0.082191781 | O8: =(O6 - O5 + 1) / (DATE(YEAR(O6), 12, 31) - DATE(YEAR(O6), 1, 1) + 1) -> 0.084931507 | P8: =(P6 - P5 + 1) / (DATE(YEAR(P6), 12, 31) - DATE(YEAR(P6), 1, 1) + 1) -> 0.082191781 | Q8: =(Q6 - Q5 + 1) / (DATE(YEAR(Q6), 12, 31) - DATE(YEAR(Q6), 1, 1) + 1) -> 0.084931507 | R8: =(R6 - R5 + 1) / (DATE(YEAR(R6), 12, 31) - DATE(YEAR(R6), 1, 1) + 1) -> 0.084931507 | ... AT8: =(AT6 - AT5 + 1) / (DATE(YEAR(AT6), 12, 31) - DATE(YEAR(AT6), 1, 1) + 1) -> 0.084931507
D10: Шаг 1. Перенесите необходимые для построения отчета о движении денежных средств данные на рабочий лист
D12: План производства и продаж
D13: ='Assumptions and inputs'!D27 -> Год | I13: ='Assumptions and inputs'!I27 -> 2028 | J13: ='Assumptions and inputs'!J27 -> 0 | K13: ='Assumptions and inputs'!K27 -> 2029 | L13: ='Assumptions and inputs'!L27 -> 2030 | M13: ='Assumptions and inputs'!M27 -> 2031 | N13: ='Assumptions and inputs'!N27 -> 2032 | O13: ='Assumptions and inputs'!O27 -> 2033
D14: ='Assumptions and inputs'!D28 -> Плановый темп роста в год | E14: ='Assumptions and inputs'!E28 -> % | I14: ='Assumptions and inputs'!I28 -> 0 | J14: ='Assumptions and inputs'!J28 -> 0 | K14: ='Assumptions and inputs'!K28 -> 0 | L14: ='Assumptions and inputs'!L28 -> 1.15 | M14: ='Assumptions and inputs'!M28 -> 0.2 | N14: ='Assumptions and inputs'!N28 -> 0.2 | O14: ='Assumptions and inputs'!O28 -> 0.2
D15: ='Assumptions and inputs'!D29 -> Плановый объем производства в год запуска проекта | E15: ='Assumptions and inputs'!E29 -> кг | I15: ='Assumptions and inputs'!I29 -> 5000000 | J15: ='Assumptions and inputs'!J29 -> 0 | K15: =I15 * (1 + K14) -> 5000000 | L15: =K15 * (1 + L14) -> 10750000 | M15: =L15 * (1 + M14) -> 12900000 | N15: =M15 * (1 + N14) -> 15480000 | O15: =N15 * (1 + O14) -> 18576000
D16: ='Assumptions and inputs'!D31 -> Месяц | K16: ='Assumptions and inputs'!K31 -> 1 | L16: ='Assumptions and inputs'!L31 -> 2 | M16: ='Assumptions and inputs'!M31 -> 3 | N16: ='Assumptions and inputs'!N31 -> 4 | O16: ='Assumptions and inputs'!O31 -> 5 | P16: ='Assumptions and inputs'!P31 -> 6 | Q16: ='Assumptions and inputs'!Q31 -> 7 | R16: ='Assumptions and inputs'!R31 -> 8 | ... V16: ='Assumptions and inputs'!V31 -> 12
D17: ='Assumptions and inputs'!D32 -> Сезонность | K17: ='Assumptions and inputs'!K32 -> 0.75 | L17: ='Assumptions and inputs'!L32 -> 0.85 | M17: ='Assumptions and inputs'!M32 -> 0.9 | N17: ='Assumptions and inputs'!N32 -> 1.1 | O17: ='Assumptions and inputs'!O32 -> 1.2 | P17: ='Assumptions and inputs'!P32 -> 1.25 | Q17: ='Assumptions and inputs'!Q32 -> 1.2 | R17: ='Assumptions and inputs'!R32 -> 1.1 | ... V17: ='Assumptions and inputs'!V32 -> 0.8
D18: ='Assumptions and inputs'!D34 -> Месяц начала продаж | E18: ='Assumptions and inputs'!E34 -> мес | H18: ='Assumptions and inputs'!H34 -> 3
D19: ='Assumptions and inputs'!D35 -> Период между производством и продажей | E19: ='Assumptions and inputs'!E35 -> мес | H19: ='Assumptions and inputs'!H35 -> 1
D22: Шаг 2. Постройте график производства
D24: График производства | E24: кг | K24: =IF(K25 = 0, 0, K28) -> 0 | L24: =IF(L25 = 0, 0, L28) -> 326027.4 | M24: =IF(M25 = 0, 0, M28) -> 382191.78 | N24: =IF(N25 = 0, 0, N28) -> 452054.79 | O24: =IF(O25 = 0, 0, O28) -> 509589.04 | P24: =IF(P25 = 0, 0, P28) -> 513698.63 | Q24: =IF(Q25 = 0, 0, Q28) -> 509589.04 | R24: =IF(R25 = 0, 0, R28) -> 467123.29 | ... AT24: =IF(AT25 = 0, 0, AT28) -> 876493.15
D25: Определение месяца начала производства | E25: bin | K25: =INT(K7 >= $H$18 - $H$19) -> 0 | L25: =INT(L7 >= $H$18 - $H$19) -> 1 | M25: =INT(M7 >= $H$18 - $H$19) -> 1 | N25: =INT(N7 >= $H$18 - $H$19) -> 1 | O25: =INT(O7 >= $H$18 - $H$19) -> 1 | P25: =INT(P7 >= $H$18 - $H$19) -> 1 | Q25: =INT(Q7 >= $H$18 - $H$19) -> 1 | R25: =INT(R7 >= $H$18 - $H$19) -> 1 | ... AT25: =INT(AT7 >= $H$18 - $H$19) -> 1
D26: Плановый годовой объем производства | E26: кг | K26: =INDEX($K$15:$O$15, , MATCH(K$4, $K$13:$O$13, 0)) -> 5000000 | L26: =INDEX($K$15:$O$15, , MATCH(L$4, $K$13:$O$13, 0)) -> 5000000 | M26: =INDEX($K$15:$O$15, , MATCH(M$4, $K$13:$O$13, 0)) -> 5000000 | N26: =INDEX($K$15:$O$15, , MATCH(N$4, $K$13:$O$13, 0)) -> 5000000 | O26: =INDEX($K$15:$O$15, , MATCH(O$4, $K$13:$O$13, 0)) -> 5000000 | P26: =INDEX($K$15:$O$15, , MATCH(P$4, $K$13:$O$13, 0)) -> 5000000 | Q26: =INDEX($K$15:$O$15, , MATCH(Q$4, $K$13:$O$13, 0)) -> 5000000 | R26: =INDEX($K$15:$O$15, , MATCH(R$4, $K$13:$O$13, 0)) -> 5000000 | ... AT26: =INDEX($K$15:$O$15, , MATCH(AT$4, $K$13:$O$13, 0)) -> 12900000
D27: Плановый объем производства за период | E27: кг | K27: =K26 * K8 -> 424657.53 | L27: =L26 * L8 -> 383561.64 | M27: =M26 * M8 -> 424657.53 | N27: =N26 * N8 -> 410958.9 | O27: =O26 * O8 -> 424657.53 | P27: =P26 * P8 -> 410958.9 | Q27: =Q26 * Q8 -> 424657.53 | R27: =R26 * R8 -> 424657.53 | ... AT27: =AT26 * AT8 -> 1095616.4
D28: Плановый объем производства за период с учетом сезонности | E28: кг | K28: =K27 * (INDEX($K$17:$V$17, , MATCH(MONTH(K5), $K$16:$V$16, 0))) -> 318493.15 | L28: =L27 * (INDEX($K$17:$V$17, , MATCH(MONTH(L5), $K$16:$V$16, 0))) -> 326027.4 | M28: =M27 * (INDEX($K$17:$V$17, , MATCH(MONTH(M5), $K$16:$V$16, 0))) -> 382191.78 | N28: =N27 * (INDEX($K$17:$V$17, , MATCH(MONTH(N5), $K$16:$V$16, 0))) -> 452054.79 | O28: =O27 * (INDEX($K$17:$V$17, , MATCH(MONTH(O5), $K$16:$V$16, 0))) -> 509589.04 | P28: =P27 * (INDEX($K$17:$V$17, , MATCH(MONTH(P5), $K$16:$V$16, 0))) -> 513698.63 | Q28: =Q27 * (INDEX($K$17:$V$17, , MATCH(MONTH(Q5), $K$16:$V$16, 0))) -> 509589.04 | R28: =R27 * (INDEX($K$17:$V$17, , MATCH(MONTH(R5), $K$16:$V$16, 0))) -> 467123.29 | ... AT28: =AT27 * (INDEX($K$17:$V$17, , MATCH(MONTH(AT5), $K$16:$V$16, 0))) -> 876493.15
D31: Шаг 3 Постройте график продаж
D33: График продаж | E33: кг | K33: =IF(K7 < $H$19, 0, OFFSET(K24, 0, - 1 * $H$19)) -> 0 | L33: =IF(L7 < $H$19, 0, OFFSET(L24, 0, - 1 * $H$19)) -> 0 | M33: =IF(M7 < $H$19, 0, OFFSET(M24, 0, - 1 * $H$19)) -> 326027.4 | N33: =IF(N7 < $H$19, 0, OFFSET(N24, 0, - 1 * $H$19)) -> 382191.78 | O33: =IF(O7 < $H$19, 0, OFFSET(O24, 0, - 1 * $H$19)) -> 452054.79 | P33: =IF(P7 < $H$19, 0, OFFSET(P24, 0, - 1 * $H$19)) -> 509589.04 | Q33: =IF(Q7 < $H$19, 0, OFFSET(Q24, 0, - 1 * $H$19)) -> 513698.63 | R33: =IF(R7 < $H$19, 0, OFFSET(R24, 0, - 1 * $H$19)) -> 509589.04 | ... AT33: =IF(AT7 < $H$19, 0, OFFSET(AT24, 0, - 1 * $H$19)) -> 901232.88
D34: Справочно: плановый объем продаж в год | K34: =SUMIF($K$4:$AU$4, K$13, $K$33:$AU$33) -> 4344520.5 | L34: =SUMIF($K$4:$AU$4, L$13, $K$33:$AU$33) -> 10365205 | M34: =SUMIF($K$4:$AU$4, M$13, $K$33:$AU$33) -> 12760986

Sheet Себестоимость
D1: ToolKit Финансы. Блок Финансовое моделирование. Расчет себестоимости и определение цены продукта
D3: Временные шкалы
E4: Ед.изм. | F4: Комментарий | G4: Проверка | H4: Фикс.значения * | I4: База * | K4: =YEAR(K5) -> 2029 | L4: =YEAR(L5) -> 2029 | M4: =YEAR(M5) -> 2029 | N4: =YEAR(N5) -> 2029 | O4: =YEAR(O5) -> 2029 | P4: =YEAR(P5) -> 2029 | Q4: =YEAR(Q5) -> 2029 | R4: =YEAR(R5) -> 2029 | ... AU4: =YEAR(AU5) -> 2032
D5: Начало периода | E5: дата | K5: =I6 + 1 -> 47119 | L5: =K6 + 1 -> 47150 | M5: =L6 + 1 -> 47178 | N5: =M6 + 1 -> 47209 | O5: =N6 + 1 -> 47239 | P5: =O6 + 1 -> 47270 | Q5: =P6 + 1 -> 47300 | R5: =Q6 + 1 -> 47331 | S5: =R6 + 1 -> 47362 | ... AU5: =AT6 + 1 -> 48214
D6: Конец периода | E6: дата | I6: ='Assumptions and inputs'!I8 -> 47118 | K6: =EOMONTH(K5, 0) -> 47149 | L6: =EOMONTH(L5, 0) -> 47177 | M6: =EOMONTH(M5, 0) -> 47208 | N6: =EOMONTH(N5, 0) -> 47238 | O6: =EOMONTH(O5, 0) -> 47269 | P6: =EOMONTH(P5, 0) -> 47299 | Q6: =EOMONTH(Q5, 0) -> 47330 | R6: =EOMONTH(R5, 0) -> 47361 | ... AT6: =EOMONTH(AT5, 0) -> 48213 | AU6: =EOMONTH(AU5, 0) + 1 -> 48245
D7: Номер периода | I7: 0 | K7: =I7 + 1 -> 1 | L7: =K7 + 1 -> 2 | M7: =L7 + 1 -> 3 | N7: =M7 + 1 -> 4 | O7: =N7 + 1 -> 5 | P7: =O7 + 1 -> 6 | Q7: =P7 + 1 -> 7 | R7: =Q7 + 1 -> 8 | S7: =R7 + 1 -> 9 | ... AU7: =AT7 + 1 -> 37
D8: Длина периода | K8: =(K6 - K5 + 1)/ (DATE(YEAR(K6), 12, 31) - DATE(YEAR(K6), 1, 1) + 1) -> 0.084931507 | L8: =(L6 - L5 + 1)/ (DATE(YEAR(L6), 12, 31) - DATE(YEAR(L6), 1, 1) + 1) -> 0.076712329 | M8: =(M6 - M5 + 1)/ (DATE(YEAR(M6), 12, 31) - DATE(YEAR(M6), 1, 1) + 1) -> 0.084931507 | N8: =(N6 - N5 + 1)/ (DATE(YEAR(N6), 12, 31) - DATE(YEAR(N6), 1, 1) + 1) -> 0.082191781 | O8: =(O6 - O5 + 1)/ (DATE(YEAR(O6), 12, 31) - DATE(YEAR(O6), 1, 1) + 1) -> 0.084931507 | P8: =(P6 - P5 + 1)/ (DATE(YEAR(P6), 12, 31) - DATE(YEAR(P6), 1, 1) + 1) -> 0.082191781 | Q8: =(Q6 - Q5 + 1)/ (DATE(YEAR(Q6), 12, 31) - DATE(YEAR(Q6), 1, 1) + 1) -> 0.084931507 | R8: =(R6 - R5 + 1)/ (DATE(YEAR(R6), 12, 31) - DATE(YEAR(R6), 1, 1) + 1) -> 0.084931507 | ... AT8: =(AT6 - AT5 + 1)/ (DATE(YEAR(AT6), 12, 31) - DATE(YEAR(AT6), 1, 1) + 1) -> 0.084931507 | AU8: =(AU6-AU5)/365 -> 0.084931507
D10: Шаг 1. Определить, какие затраты относятся к прямым, какие к косвенным. Рассчитать прямые затраты на производство 1 кг продукта.
D11: Прямые затраты
D12: Стоимость сырья
D13: Кокосовая паста | E13: руб/кг | I13: ='Assumptions and inputs'!I45 -> 380
D14: Карбонат кальция | E14: руб/кг | I14: ='Assumptions and inputs'!I46 -> 75
D15: Витамины | E15: руб/кг | I15: ='Assumptions and inputs'!I47 -> 4500
D16: Камедь рожкового дерева | E16: руб/кг | I16: ='Assumptions and inputs'!I48 -> 1500
D17: Лецитин подсолнечный | E17: руб/кг | I17: ='Assumptions and inputs'!I49 -> 234
D19: Состав 1 кг продукта
D20: Основа - кокосовая паста | E20: кг | I20: ='Assumptions and inputs'!I51 -> 0.17
D21: Кальций | E21: кг | I21: ='Assumptions and inputs'!I52 -> 0.01
D22: Витамины | E22: кг | I22: ='Assumptions and inputs'!I53 -> 0.007
D23: Стабилизатор (камедь рожкового дерева) | E23: кг | I23: ='Assumptions and inputs'!I54 -> 0.008
D24: Эмульгатор (лецитин подсолнечный) | E24: кг | I24: ='Assumptions and inputs'!I55 -> 0.005
D25: Вода | E25: кг | I25: ='Assumptions and inputs'!I56 -> 0.8
D27: Прямые затраты на производство 1 кг продукта | E27: руб/кг | F27: 1 кг эквивалентен 1 л = 1 упаковка молока | I27: =I28+I34+I35 -> 135.02
D28: Сырье | E28: руб | I28: =SUM(I29:I33) -> 110.02
D29: =D13 -> Кокосовая паста | E29: руб | I29: =I13*I20 -> 64.6
D30: =D14 -> Карбонат кальция | E30: руб | I30: =I14*I21 -> 0.75
D31: =D15 -> Витамины | E31: руб | I31: =I15*I22 -> 31.5
D32: =D16 -> Камедь рожкового дерева | E32: руб | I32: =I16*I23 -> 12
D33: =D17 -> Лецитин подсолнечный | E33: руб | I33: =I17*I24 -> 1.17
D34: Заработная плата производственным рабочим | E34: руб | I34: ='Assumptions and inputs'!I59 -> 20
D35: Прочие прямые затраты | E35: руб | I35: ='Assumptions and inputs'!I60 -> 5
D37: Производственные накладные расходы за год | I37: =SUM(I38:I39) -> 8500000
D38: Общие затраты по управлению цехом | E38: руб | I38: ='Assumptions and inputs'!I63 -> 4500000
D39: Затраты на наладку оборудования | E39: руб | I39: ='Assumptions and inputs'!I64 -> 4000000
D41: Прочие накладные расходы за год | I41: =SUM(I42) -> 8000000
D42: Административные расходы | E42: руб | I42: ='Assumptions and inputs'!I65 -> 8000000
D44: Шаг 2. Установить основные процессы, связанные с производством и выявить драйвер затрат по каждому процессу
D45: Процесс | F45: Драйвер
D46: Управление цехом | F46: Число произведенных партий
D47: Наладка оборудования | F47: Число переналадок оборудования
D48: Администрирование | F48: Число отгруженных партий
D50: Шаг 3. Рассчитать значение носителя затрат (число операций по каждому процессу) | I50: =YEAR(I6) -> 2028 | K50: =I50 + 1 -> 2029 | L50: =K50 + 1 -> 2030 | M50: =L50 + 1 -> 2031
D51: Объем производства | E51: кг | K51: =Прогнозы!K15 -> 5000000 | L51: =Прогнозы!L15 -> 10750000 | M51: =Прогнозы!M15 -> 12900000
D53: Шаг 4. Рассчитать ставки драйверов затрат по каждому процессу | F53: (= затраты / значение носителя) | K53: =K50 -> 2029 | L53: =L50 -> 2030 | M53: =M50 -> 2031
D54: Ставки драйверов затрат по процессам
D55: =D46 -> Управление цехом | E55: руб/кг | K55: =$I$38 / K51 -> 0.9 | L55: =$I$38 / L51 -> 0.41860465 | M55: =$I$38 / M51 -> 0.34883721
D56: =D47 -> Наладка оборудования | E56: руб/кг | K56: =$I$39 / K51 -> 0.8 | L56: =$I$39 / L51 -> 0.37209302 | M56: =$I$39 / M51 -> 0.31007752
D57: =D48 -> Администрирование | E57: руб/кг | K57: =$I$42/K51 -> 1.6 | L57: =$I$42/L51 -> 0.74418605 | M57: =$I$42/M51 -> 0.62015504
D59: Шаг 5. Рассчитать себестоимость 1 кг продукции. | K59: =K50 -> 2029 | L59: =L50 -> 2030 | M59: =M50 -> 2031
D60: =D27 -> Прямые затраты на производство 1 кг продукта | E60: руб | I60: =I27 -> 135.02 | K60: =$I60 -> 135.02 | L60: =K60 -> 135.02 | M60: =L60 -> 135.02
D61: =D28 -> Сырье | E61: =E28 -> руб | I61: =I28 -> 110.02 | K61: =$I61 -> 110.02 | L61: =K61 -> 110.02 | M61: =L61 -> 110.02
D62: =D34 -> Заработная плата производственным рабочим | E62: =E34 -> руб | I62: =I34 -> 20 | K62: =$I62 -> 20 | L62: =K62 -> 20 | M62: =L62 -> 20
D63: =D35 -> Прочие прямые затраты | E63: =E35 -> руб | I63: =I35 -> 5 | K63: =$I63 -> 5 | L63: =K63 -> 5 | M63: =L63 -> 5
D65: Косвенные затраты | K65: =SUM(K66:K68) -> 3.3 | L65: =SUM(L66:L68) -> 1.5348837 | M65: =SUM(M66:M68) -> 1.2790698
D66: =D38 -> Общие затраты по управлению цехом | E66: =E38 -> руб | K66: =K55 -> 0.9 | L66: =L55 -> 0.41860465 | M66: =M55 -> 0.34883721
D67: =D39 -> Затраты на наладку оборудования | E67: =E39 -> руб | K67: =K56 -> 0.8 | L67: =L56 -> 0.37209302 | M67: =M56 -> 0.31007752
D68: =D42 -> Административные расходы | E68: =E42 -> руб | K68: =K57 -> 1.6 | L68: =L57 -> 0.74418605 | M68: =M57 -> 0.62015504
D70: Итого себестоимость продукта | F70: без учета инфляции | K70: =K60+K65 -> 138.32 | L70: =L60+L65 -> 136.55488 | M70: =M60+M65 -> 136.29907
D72: Шаг 6. Определить цену 1 кг продукта. Для расчета цены взять за значение себестоимости за 3 год (после выхода на полную мощность производства) и ожидаемую рентабельность
D73: ='Assumptions and inputs'!D41 -> Рентабельность аналогичных продуктов в компании | H73: ='Assumptions and inputs'!H41 -> 0.45
D74: Средняя себестоимость продукта | E74: руб | I74: =M70 -> 136.29907
D75: Наценка | E75: руб | I75: =I74 * H73 / (1 - H73) -> 111.51742
D76: Цена | E76: руб | I76: =I75+I74 -> 247.81649

Sheet CF
D1: ToolKit Финансы. Блок Финансовое моделирование. Cash Flows
D3: Временные шкалы
E4: Ед.изм. | F4: Комментарий | G4: Проверка | H4: Фикс.значения * | I4: База * | K4: =YEAR(K5) -> 2029 | L4: =YEAR(L5) -> 2029 | M4: =YEAR(M5) -> 2029 | N4: =YEAR(N5) -> 2029 | O4: =YEAR(O5) -> 2029 | P4: =YEAR(P5) -> 2029 | Q4: =YEAR(Q5) -> 2029 | R4: =YEAR(R5) -> 2029 | ... AT4: =YEAR(AT5) -> 2031
D5: Начало периода | E5: дата | K5: =I6 + 1 -> 47119 | L5: =K6 + 1 -> 47150 | M5: =L6 + 1 -> 47178 | N5: =M6 + 1 -> 47209 | O5: =N6 + 1 -> 47239 | P5: =O6 + 1 -> 47270 | Q5: =P6 + 1 -> 47300 | R5: =Q6 + 1 -> 47331 | S5: =R6 + 1 -> 47362 | ... AT5: =AS6 + 1 -> 48183
D6: Конец периода | E6: дата | I6: ='Assumptions and inputs'!I8 -> 47118 | K6: =EOMONTH(K5, 0) -> 47149 | L6: =EOMONTH(L5, 0) -> 47177 | M6: =EOMONTH(M5, 0) -> 47208 | N6: =EOMONTH(N5, 0) -> 47238 | O6: =EOMONTH(O5, 0) -> 47269 | P6: =EOMONTH(P5, 0) -> 47299 | Q6: =EOMONTH(Q5, 0) -> 47330 | R6: =EOMONTH(R5, 0) -> 47361 | ... AT6: =EOMONTH(AT5, 0) -> 48213
D7: Номер периода | I7: 0 | K7: =I7 + 1 -> 1 | L7: =K7 + 1 -> 2 | M7: =L7 + 1 -> 3 | N7: =M7 + 1 -> 4 | O7: =N7 + 1 -> 5 | P7: =O7 + 1 -> 6 | Q7: =P7 + 1 -> 7 | R7: =Q7 + 1 -> 8 | S7: =R7 + 1 -> 9 | ... AT7: =AS7 + 1 -> 36
D8: Длина периода | K8: =(K6 - K5 + 1) / (DATE(YEAR(K6), 12, 31) - DATE(YEAR(K6), 1, 1) + 1) -> 0.084931507 | L8: =(L6 - L5 + 1) / (DATE(YEAR(L6), 12, 31) - DATE(YEAR(L6), 1, 1) + 1) -> 0.076712329 | M8: =(M6 - M5 + 1) / (DATE(YEAR(M6), 12, 31) - DATE(YEAR(M6), 1, 1) + 1) -> 0.084931507 | N8: =(N6 - N5 + 1) / (DATE(YEAR(N6), 12, 31) - DATE(YEAR(N6), 1, 1) + 1) -> 0.082191781 | O8: =(O6 - O5 + 1) / (DATE(YEAR(O6), 12, 31) - DATE(YEAR(O6), 1, 1) + 1) -> 0.084931507 | P8: =(P6 - P5 + 1) / (DATE(YEAR(P6), 12, 31) - DATE(YEAR(P6), 1, 1) + 1) -> 0.082191781 | Q8: =(Q6 - Q5 + 1) / (DATE(YEAR(Q6), 12, 31) - DATE(YEAR(Q6), 1, 1) + 1) -> 0.084931507 | R8: =(R6 - R5 + 1) / (DATE(YEAR(R6), 12, 31) - DATE(YEAR(R6), 1, 1) + 1) -> 0.084931507 | ... AT8: =(AT6 - AT5 + 1) / (DATE(YEAR(AT6), 12, 31) - DATE(YEAR(AT6), 1, 1) + 1) -> 0.084931507
D10: Шаг 1. Перенесите необходимые для построения отчета о движении денежных средств данные на рабочий лист
D12: Инфляция | K12: ='Assumptions and inputs'!K18 -> 0.0040182019 | L12: ='Assumptions and inputs'!L18 -> 0.0036156562 | M12: ='Assumptions and inputs'!M18 -> 0.0040182019 | N12: ='Assumptions and inputs'!N18 -> 0.0038840021 | O12: ='Assumptions and inputs'!O18 -> 0.0040182019 | P12: ='Assumptions and inputs'!P18 -> 0.0038840021 | Q12: ='Assumptions and inputs'!Q18 -> 0.0040182019 | R12: ='Assumptions and inputs'!R18 -> 0.0040182019 | ... AT12: ='Assumptions and inputs'!AT18 -> 0.0032288217
D13: Инфляция кумулятивно | K13: ='Assumptions and inputs'!K19 -> 1.0040182 | L13: ='Assumptions and inputs'!L19 -> 1.0076484 | M13: ='Assumptions and inputs'!M19 -> 1.0116973 | N13: ='Assumptions and inputs'!N19 -> 1.0156268 | O13: ='Assumptions and inputs'!O19 -> 1.0197077 | P13: ='Assumptions and inputs'!P19 -> 1.0236683 | Q13: ='Assumptions and inputs'!Q19 -> 1.0277816 | R13: ='Assumptions and inputs'!R19 -> 1.0319114 | ... AT13: ='Assumptions and inputs'!AT19 -> 1.128836
D15: Объем продаж и цены реализации
D16: Продажи | E16: кг | K16: =Прогнозы!K33 -> 0 | L16: =Прогнозы!L33 -> 0 | M16: =Прогнозы!M33 -> 326027.4 | N16: =Прогнозы!N33 -> 382191.78 | O16: =Прогнозы!O33 -> 452054.79 | P16: =Прогнозы!P33 -> 509589.04 | Q16: =Прогнозы!Q33 -> 513698.63 | R16: =Прогнозы!R33 -> 509589.04 | ... AT16: =Прогнозы!AT33 -> 901232.88
D17: Динамика цен (вкл. НДС) | E17: руб | I17: =Себестоимость!I76 -> 247.81649 | K17: =I17 -> 247.81649 | L17: =K17 * (1 + L12) -> 248.71251 | M17: =L17 * (1 + M12) -> 249.71189 | N17: =M17 * (1 + N12) -> 250.68177 | O17: =N17 * (1 + O12) -> 251.68906 | P17: =O17 * (1 + P12) -> 252.66662 | Q17: =P17 * (1 + Q12) -> 253.68188 | R17: =Q17 * (1 + R12) -> 254.70123 | S17: =R17 * (1 + S12) -> 255.69049 | ... AT17: =AS17 * (1 + AT12) -> 278.6246
D19: График производства
D20: Себестоимость | E20: руб | K20: =INDEX(Себестоимость!$K$70:$M$70, 1, MATCH(K$4, Себестоимость!$K$59:$M$59, 0)) -> 138.32 | L20: =INDEX(Себестоимость!$K$70:$M$70, 1, MATCH(L$4, Себестоимость!$K$59:$M$59, 0)) -> 138.32 | M20: =INDEX(Себестоимость!$K$70:$M$70, 1, MATCH(M$4, Себестоимость!$K$59:$M$59, 0)) -> 138.32 | N20: =INDEX(Себестоимость!$K$70:$M$70, 1, MATCH(N$4, Себестоимость!$K$59:$M$59, 0)) -> 138.32 | O20: =INDEX(Себестоимость!$K$70:$M$70, 1, MATCH(O$4, Себестоимость!$K$59:$M$59, 0)) -> 138.32 | P20: =INDEX(Себестоимость!$K$70:$M$70, 1, MATCH(P$4, Себестоимость!$K$59:$M$59, 0)) -> 138.32 | Q20: =INDEX(Себестоимость!$K$70:$M$70, 1, MATCH(Q$4, Себестоимость!$K$59:$M$59, 0)) -> 138.32 | R20: =INDEX(Себестоимость!$K$70:$M$70, 1, MATCH(R$4, Себестоимость!$K$59:$M$59, 0)) -> 138.32 | ... AT20: =INDEX(Себестоимость!$K$70:$M$70, 1, MATCH(AT$4, Себестоимость!$K$59:$M$59, 0)) -> 136.29907
D21: Себестоимость с учетом инфляции | E21: руб | K21: =K20 -> 138.32 | L21: =L20 * L13 -> 139.37792 | M21: =M20 * M13 -> 139.93797 | N21: =N20 * N13 -> 140.48149 | O21: =O20 * O13 -> 141.04598 | P21: =P20 * P13 -> 141.5938 | Q21: =Q20 * Q13 -> 142.16275 | R21: =R20 * R13 -> 142.73399 | S21: =S20 * S13 -> 143.28837 | ... AT21: =AT20 * AT13 -> 153.85929
D22: График производства | E22: кг | K22: =Прогнозы!K24 -> 0 | L22: =Прогнозы!L24 -> 326027.4 | M22: =Прогнозы!M24 -> 382191.78 | N22: =Прогнозы!N24 -> 452054.79 | O22: =Прогнозы!O24 -> 509589.04 | P22: =Прогнозы!P24 -> 513698.63 | Q22: =Прогнозы!Q24 -> 509589.04 | R22: =Прогнозы!R24 -> 467123.29 | ... AT22: =Прогнозы!AT24 -> 876493.15
D24: ='Assumptions and inputs'!D21 -> Налог на прибыль | E24: ='Assumptions and inputs'!E21 -> % | H24: ='Assumptions and inputs'!H21 -> 0.2 | I24: ='Assumptions and inputs'!I21 -> 0
D25: ='Assumptions and inputs'!D22 -> НДС | E25: ='Assumptions and inputs'!E22 -> % | H25: ='Assumptions and inputs'!H22 -> 0.2 | I25: ='Assumptions and inputs'!I22 -> 0
D27: Шаг 2. Рассчитайте свободный денежный поток на фирму (FCFF)
D29: Cвободный денежный поток на фирму (FCFF)
D31: Результат операционной деятельности | K31: =K32 - K33 - K37 - K38 -> 0 | L31: =L32 - L33 - L37 - L38 -> -45441022 | M31: =M32 - M33 - M37 - M38 -> 7576544.1 | N31: =N32 - N33 - N37 - N38 -> 8351051.2 | O31: =O32 - O33 - O37 - O38 -> 13457451 | P31: =P32 - P33 - P37 - P38 -> 23016153 | Q31: =Q32 - Q33 - Q37 - Q38 -> 23249411 | R31: =R32 - R33 - R37 - R38 -> 28643839 | ... AT31: =AT32 - AT33 - AT37 - AT38 -> 38357820
D32: Денежные поступления от операционной деятельности | E32: руб | K32: =K16 * K17 -> 0 | L32: =L16 * L17 -> 0 | M32: =M16 * M17 -> 81412917 | N32: =N16 * N17 -> 95808511 | O32: =O16 * O17 -> 1.1377725e+08 | P32: =P16 * P17 -> 1.2875614e+08 | Q32: =Q16 * Q17 -> 1.3031604e+08 | R32: =R16 * R17 -> 1.2979296e+08 | ... AT32: =AT16 * AT17 -> 2.5110565e+08
D33: Платежи по операционной деятельности | E33: руб | K33: =SUM(K34:K36) -> 0 | L33: =SUM(L34:L36) -> 45441022 | M33: =SUM(M34:M36) -> 73836372 | N33: =SUM(N34:N36) -> 87457460 | O33: =SUM(O34:O36) -> 1.0031979e+08 | P33: =SUM(P34:P36) -> 1.0492558e+08 | Q33: =SUM(Q34:Q36) -> 1.0502359e+08 | R33: =SUM(R34:R36) -> 99122609 | ... AT33: =SUM(AT34:AT36) -> 1.9763303e+08
D34: Себестоимость производства | E34: руб | K34: =K21 * K22 -> 0 | L34: =L21 * L22 -> 45441022 | M34: =M21 * M22 -> 53483143 | N34: =N21 * N22 -> 63505332 | O34: =O21 * O22 -> 71875484 | P34: =P21 * P22 -> 72736540 | Q34: =Q21 * Q22 -> 72444580 | R34: =R21 * R22 -> 66674371 | ... AT34: =AT21 * AT22 -> 1.3485662e+08
D35: Маркетинг | E35: руб | F35: Процент от выручки | H35: ='Assumptions and inputs'!H88 -> 0.15 | K35: =K32 * $H$35 -> 0 | L35: =L32 * $H$35 -> 0 | M35: =M32 * $H$35 -> 12211937 | N35: =N32 * $H$35 -> 14371277 | O35: =O32 * $H$35 -> 17066587 | P35: =P32 * $H$35 -> 19313421 | Q35: =Q32 * $H$35 -> 19547405 | R35: =R32 * $H$35 -> 19468943 | ... AT35: =AT32 * $H$35 -> 37665847
D36: АУП и непредвиденные затраты | E36: руб | F36: Процент от выручки | H36: ='Assumptions and inputs'!H89 -> 0.1 | K36: =K32 * $H$36 -> 0 | L36: =L32 * $H$36 -> 0 | M36: =M32 * $H$36 -> 8141291.7 | N36: =N32 * $H$36 -> 9580851.1 | O36: =O32 * $H$36 -> 11377725 | P36: =P32 * $H$36 -> 12875614 | Q36: =Q32 * $H$36 -> 13031604 | R36: =R32 * $H$36 -> 12979296 | ... AT36: =AT32 * $H$36 -> 25110565
D37: Налог на прибыль | K37: ='P&L'!K37 -> 0 | L37: ='P&L'!L37 -> 0 | M37: ='P&L'!M37 -> 0 | N37: ='P&L'!N37 -> 0 | O37: ='P&L'!O37 -> 0 | P37: ='P&L'!P37 -> 814411.21 | Q37: ='P&L'!Q37 -> 2043036.1 | R37: ='P&L'!R37 -> 2026506.6 | ... AT37: ='P&L'!AT37 -> 6202697.3
D38: НДС | K38: =K41 + SUM(K44:K45) -> 0 | L38: =L41 + SUM(L44:L45) -> 0 | M38: =M41 + SUM(M44:M45) -> 0 | N38: =N41 + SUM(N44:N45) -> 0 | O38: =O41 + SUM(O44:O45) -> 0 | P38: =P41 + SUM(P44:P45) -> 0 | Q38: =Q41 + SUM(Q44:Q45) -> 0 | R38: =R41 + SUM(R44:R45) -> 0 | ... AT38: =AT41 + SUM(AT44:AT45) -> 8912103.4
D39: НДС в продажах | E39: руб | K39: =(K32 / (1 + $H$25)) * $H$25 -> 0 | L39: =(L32 / (1 + $H$25)) * $H$25 -> 0 | M39: =(M32 / (1 + $H$25)) * $H$25 -> 13568819 | N39: =(N32 / (1 + $H$25)) * $H$25 -> 15968085 | O39: =(O32 / (1 + $H$25)) * $H$25 -> 18962874 | P39: =(P32 / (1 + $H$25)) * $H$25 -> 21459357 | Q39: =(Q32 / (1 + $H$25)) * $H$25 -> 21719339 | R39: =(R32 / (1 + $H$25)) * $H$25 -> 21632159 | ... AT39: =(AT32 / (1 + $H$25)) * $H$25 -> 41850942
D40: НДС в затратах | E40: руб | K40: =(SUM(K33, K48) / (1 + $H$25)) * $H$25 -> 49583333 | L40: =(SUM(L33, L48) / (1 + $H$25)) * $H$25 -> 57156837 | M40: =(SUM(M33, M48) / (1 + $H$25)) * $H$25 -> 12306062 | N40: =(SUM(N33, N48) / (1 + $H$25)) * $H$25 -> 14576243 | O40: =(SUM(O33, O48) / (1 + $H$25)) * $H$25 -> 16719966 | P40: =(SUM(P33, P48) / (1 + $H$25)) * $H$25 -> 17487596 | Q40: =(SUM(Q33, Q48) / (1 + $H$25)) * $H$25 -> 17503932 | R40: =(SUM(R33, R48) / (1 + $H$25)) * $H$25 -> 16520435 | ... AT40: =(SUM(AT33, AT48) / (1 + $H$25)) * $H$25 -> 32938838
D41: Сальдо по НДС в периоде | E41: руб | K41: =K39 - K40 -> -49583333 | L41: =L39 - L40 -> -57156837 | M41: =M39 - M40 -> 1262757.4 | N41: =N39 - N40 -> 1391841.9 | O41: =O39 - O40 -> 2242908.4 | P41: =P39 - P40 -> 3971760.8 | Q41: =Q39 - Q40 -> 4215407.9 | R41: =R39 - R40 -> 5111724.3 | ... AT41: =AT39 - AT40 -> 8912103.4
D43: НДС к возмещению b-o-p | E43: руб | K43: =J46 -> 0 | L43: =K46 -> 49583333 | M43: =L46 -> 1.0674017e+08 | N43: =M46 -> 1.0547741e+08 | O43: =N46 -> 1.0408557e+08 | P43: =O46 -> 1.0184266e+08 | Q43: =P46 -> 97870902 | R43: =Q46 -> 93655494 | ... AT43: =AS46 -> 0
D44: Накопление НДС | E44: руб | K44: =- K41 * (K41 < 0) -> 49583333 | L44: =- L41 * (L41 < 0) -> 57156837 | M44: =- M41 * (M41 < 0) -> 0 | N44: =- N41 * (N41 < 0) -> 0 | O44: =- O41 * (O41 < 0) -> 0 | P44: =- P41 * (P41 < 0) -> 0 | Q44: =- Q41 * (Q41 < 0) -> 0 | R44: =- R41 * (R41 < 0) -> 0 | ... AT44: =- AT41 * (AT41 < 0) -> 0
D45: Возмещение НДС | E45: руб | K45: =- MIN(SUM(K43:K44), K41 * (K41 > 0)) -> 0 | L45: =- MIN(SUM(L43:L44), L41 * (L41 > 0)) -> 0 | M45: =- MIN(SUM(M43:M44), M41 * (M41 > 0)) -> -1262757.4 | N45: =- MIN(SUM(N43:N44), N41 * (N41 > 0)) -> -1391841.9 | O45: =- MIN(SUM(O43:O44), O41 * (O41 > 0)) -> -2242908.4 | P45: =- MIN(SUM(P43:P44), P41 * (P41 > 0)) -> -3971760.8 | Q45: =- MIN(SUM(Q43:Q44), Q41 * (Q41 > 0)) -> -4215407.9 | R45: =- MIN(SUM(R43:R44), R41 * (R41 > 0)) -> -5111724.3 | ... AT45: =- MIN(SUM(AT43:AT44), AT41 * (AT41 > 0)) -> 0
D46: НДС к возмещению e-o-p | E46: руб | K46: =SUM(K43:K45) -> 49583333 | L46: =SUM(L43:L45) -> 1.0674017e+08 | M46: =SUM(M43:M45) -> 1.0547741e+08 | N46: =SUM(N43:N45) -> 1.0408557e+08 | O46: =SUM(O43:O45) -> 1.0184266e+08 | P46: =SUM(P43:P45) -> 97870902 | Q46: =SUM(Q43:Q45) -> 93655494 | R46: =SUM(R43:R45) -> 88543770 | ... AT46: =SUM(AT43:AT45) -> 0
D48: Результаты инвестиционной деятельности | K48: =K49 + K54 + K57 -> 297500000 | L48: =L49 + L54 + L57 -> 297500000 | M48: =M49 + M54 + M57 -> 0 | N48: =N49 + N54 + N57 -> 0 | O48: =O49 + O54 + O57 -> 0 | P48: =P49 + P54 + P57 -> 0 | Q48: =Q49 + Q54 + Q57 -> 0 | R48: =R49 + R54 + R57 -> 0 | ... AT48: =AT49 + AT54 + AT57 -> 0
D49: ='Assumptions and inputs'!D77 -> Процессное оборудование | K49: =SUM(K50:K53) -> 152500000 | L49: =SUM(L50:L53) -> 152500000 | M49: =SUM(M50:M53) -> 0 | N49: =SUM(N50:N53) -> 0 | O49: =SUM(O50:O53) -> 0 | P49: =SUM(P50:P53) -> 0 | Q49: =SUM(Q50:Q53) -> 0 | R49: =SUM(R50:R53) -> 0 | ... AT49: =SUM(AT50:AT53) -> 0
D50: ='Assumptions and inputs'!D78 -> Приемка сырья | E50: ='Assumptions and inputs'!E78 -> руб. | K50: ='Assumptions and inputs'!K78 -> 45000000 | L50: ='Assumptions and inputs'!L78 -> 45000000 | M50: ='Assumptions and inputs'!M78 -> 0 | N50: ='Assumptions and inputs'!N78 -> 0 | O50: ='Assumptions and inputs'!O78 -> 0 | P50: ='Assumptions and inputs'!P78 -> 0 | Q50: ='Assumptions and inputs'!Q78 -> 0 | R50: ='Assumptions and inputs'!R78 -> 0 | ... AT50: ='Assumptions and inputs'!AT78 -> 0
D51: ='Assumptions and inputs'!D79 -> Миксинг | E51: ='Assumptions and inputs'!E79 -> руб. | K51: ='Assumptions and inputs'!K79 -> 35000000 | L51: ='Assumptions and inputs'!L79 -> 35000000 | M51: ='Assumptions and inputs'!M79 -> 0 | N51: ='Assumptions and inputs'!N79 -> 0 | O51: ='Assumptions and inputs'!O79 -> 0 | P51: ='Assumptions and inputs'!P79 -> 0 | Q51: ='Assumptions and inputs'!Q79 -> 0 | R51: ='Assumptions and inputs'!R79 -> 0 | ... AT51: ='Assumptions and inputs'!AT79 -> 0
D52: ='Assumptions and inputs'!D80 -> Декантация и деактивация | E52: ='Assumptions and inputs'!E80 -> руб. | K52: ='Assumptions and inputs'!K80 -> 27500000 | L52: ='Assumptions and inputs'!L80 -> 27500000 | M52: ='Assumptions and inputs'!M80 -> 0 | N52: ='Assumptions and inputs'!N80 -> 0 | O52: ='Assumptions and inputs'!O80 -> 0 | P52: ='Assumptions and inputs'!P80 -> 0 | Q52: ='Assumptions and inputs'!Q80 -> 0 | R52: ='Assumptions and inputs'!R80 -> 0 | ... AT52: ='Assumptions and inputs'!AT80 -> 0
D53: ='Assumptions and inputs'!D81 -> Гомогенизация и стерилизация | E53: ='Assumptions and inputs'!E81 -> руб. | K53: ='Assumptions and inputs'!K81 -> 45000000 | L53: ='Assumptions and inputs'!L81 -> 45000000 | M53: ='Assumptions and inputs'!M81 -> 0 | N53: ='Assumptions and inputs'!N81 -> 0 | O53: ='Assumptions and inputs'!O81 -> 0 | P53: ='Assumptions and inputs'!P81 -> 0 | Q53: ='Assumptions and inputs'!Q81 -> 0 | R53: ='Assumptions and inputs'!R81 -> 0 | ... AT53: ='Assumptions and inputs'!AT81 -> 0
D54: ='Assumptions and inputs'!D82 -> Упаковочная линия | K54: =SUM(K55:K56) -> 55000000 | L54: =SUM(L55:L56) -> 55000000 | M54: =SUM(M55:M56) -> 0 | N54: =SUM(N55:N56) -> 0 | O54: =SUM(O55:O56) -> 0 | P54: =SUM(P55:P56) -> 0 | Q54: =SUM(Q55:Q56) -> 0 | R54: =SUM(R55:R56) -> 0 | ... AT54: =SUM(AT55:AT56) -> 0
D55: ='Assumptions and inputs'!D83 -> Фасовка | E55: ='Assumptions and inputs'!E83 -> руб. | K55: ='Assumptions and inputs'!K83 -> 35000000 | L55: ='Assumptions and inputs'!L83 -> 35000000 | M55: ='Assumptions and inputs'!M83 -> 0 | N55: ='Assumptions and inputs'!N83 -> 0 | O55: ='Assumptions and inputs'!O83 -> 0 | P55: ='Assumptions and inputs'!P83 -> 0 | Q55: ='Assumptions and inputs'!Q83 -> 0 | R55: ='Assumptions and inputs'!R83 -> 0 | ... AT55: ='Assumptions and inputs'!AT83 -> 0
D56: ='Assumptions and inputs'!D84 -> Группировка | E56: ='Assumptions and inputs'!E84 -> руб. | K56: ='Assumptions and inputs'!K84 -> 20000000 | L56: ='Assumptions and inputs'!L84 -> 20000000 | M56: ='Assumptions and inputs'!M84 -> 0 | N56: ='Assumptions and inputs'!N84 -> 0 | O56: ='Assumptions and inputs'!O84 -> 0 | P56: ='Assumptions and inputs'!P84 -> 0 | Q56: ='Assumptions and inputs'!Q84 -> 0 | R56: ='Assumptions and inputs'!R84 -> 0 | ... AT56: ='Assumptions and inputs'!AT84 -> 0
D57: ='Assumptions and inputs'!D85 -> Работа над технологией | E57: ='Assumptions and inputs'!E85 -> руб. | K57: ='Assumptions and inputs'!K85 -> 90000000 | L57: ='Assumptions and inputs'!L85 -> 90000000 | M57: ='Assumptions and inputs'!M85 -> 0 | N57: ='Assumptions and inputs'!N85 -> 0 | O57: ='Assumptions and inputs'!O85 -> 0 | P57: ='Assumptions and inputs'!P85 -> 0 | Q57: ='Assumptions and inputs'!Q85 -> 0 | R57: ='Assumptions and inputs'!R85 -> 0 | ... AT57: ='Assumptions and inputs'!AT85 -> 0
D59: Результаты финансовой деятельности | E59: руб | K59: =K60 - K61 -> 0 | L59: =L60 - L61 -> 0 | M59: =M60 - M61 -> 0 | N59: =N60 - N61 -> 0 | O59: =O60 - O61 -> 0 | P59: =P60 - P61 -> 0 | Q59: =Q60 - Q61 -> 0 | R59: =R60 - R61 -> 0 | ... AT59: =AT60 - AT61 -> 0
D60: Привлеченные займы и кредиты
D61: Погашение кредитов и займов
D63: Cвободный денежный поток на фирму (FCFF) | H63: =SUM(K63:AT63) -> 4.3665229e+08 | K63: =K31 - K48 + K59 -> -297500000 | L63: =L31 - L48 + L59 -> -3.4294102e+08 | M63: =M31 - M48 + M59 -> 7576544.1 | N63: =N31 - N48 + N59 -> 8351051.2 | O63: =O31 - O48 + O59 -> 13457451 | P63: =P31 - P48 + P59 -> 23016153 | Q63: =Q31 - Q48 + Q59 -> 23249411 | R63: =R31 - R48 + R59 -> 28643839 | ... AT63: =AT31 - AT48 + AT59 -> 38357820
D64: Ставка дисконта (WACC) | E64: % | H64: ='Assumptions and inputs'!H104 -> 0.11750982
D65: Ежемесячная ставка дисконта | E65: % | H65: =(1 + H64) ^ (1 / 12) - 1 -> 0.0093015628
D66: Дисконтированный денежный поток (WACC) | E66: руб | H66: =SUM(K66:AT66) -> 2.4178628e+08 | K66: =K63 / (1 + $H$65) ^ K7 -> -2.9475829e+08 | L66: =L63 / (1 + $H$65) ^ L7 -> -3.3664917e+08 | M66: =M63 / (1 + $H$65) ^ M7 -> 7368996 | N66: =N63 / (1 + $H$65) ^ N7 -> 8047432.9 | O66: =O63 / (1 + $H$65) ^ O7 -> 12848667 | P66: =P63 / (1 + $H$65) ^ P7 -> 21772438 | Q66: =Q63 / (1 + $H$65) ^ Q7 -> 21790407 | R66: =R63 / (1 + $H$65) ^ R7 -> 26598899 | ... AT66: =AT63 / (1 + $H$65) ^ AT7 -> 27485261
D68: Шаг 3. Рассчитайте свободный денежный поток на акционерный капитал (FCFE)
D70: Свободный денежный поток на акционерный капитал (FCFE)
D71: Расчет потребности в капитале | K71: =MAX(- K63 - J111, 0) -> 297500000 | L71: =MAX(- L63 - K111, 0) -> 3.4294102e+08 | M71: =MAX(- M63 - L111, 0) -> 0 | N71: =MAX(- N63 - M111, 0) -> 0 | O71: =MAX(- O63 - N111, 0) -> 0 | P71: =MAX(- P63 - O111, 0) -> 0 | Q71: =MAX(- Q63 - P111, 0) -> 0 | R71: =MAX(- R63 - Q111, 0) -> 0 | ... AT71: =MAX(- AT63 - AS111, 0) -> 0
D72: Операционный денежный поток накопительным итогом | H72: =MIN(K72:AT72) -> -6.4044102e+08 | K72: =K63 -> -297500000 | L72: =L63 + K72 -> -6.4044102e+08 | M72: =M63 + L72 -> -6.3286448e+08 | N72: =N63 + M72 -> -6.2451343e+08 | O72: =O63 + N72 -> -6.1105598e+08 | P72: =P63 + O72 -> -5.8803982e+08 | Q72: =Q63 + P72 -> -5.6479041e+08 | R72: =R63 + Q72 -> -5.3614657e+08 | S72: =S63 + R72 -> -5.1009657e+08 | ... AT72: =AT63 + AS72 -> 4.3665229e+08
D73: Дата начала выборки траншей кредита | E73: дата
D74: Компания Маруся | E74: руб | H74: =1 - 'Assumptions and inputs'!H109 -> 0.75 | K74: =MIN( - SUM($J74:J74) - $H$72 * $H74, K71) -> 297500000 | L74: =MIN( - SUM($J74:K74) - $H$72 * $H74, L71) -> 1.8283077e+08 | M74: =MIN( - SUM($J74:L74) - $H$72 * $H74, M71) -> 0 | N74: =MIN( - SUM($J74:M74) - $H$72 * $H74, N71) -> 0 | O74: =MIN( - SUM($J74:N74) - $H$72 * $H74, O71) -> 0 | P74: =MIN( - SUM($J74:O74) - $H$72 * $H74, P71) -> 0 | Q74: =MIN( - SUM($J74:P74) - $H$72 * $H74, Q71) -> 0 | R74: =MIN( - SUM($J74:Q74) - $H$72 * $H74, R71) -> 0 | ... AT74: =MIN( - SUM($J74:AS74) - $H$72 * $H74, AT71) -> 0
D75: Инвестор/кредитор | E75: руб | H75: ='Assumptions and inputs'!H109 -> 0.25 | K75: =K71 - K74 -> 0 | L75: =L71 - L74 -> 1.6011026e+08 | M75: =M71 - M74 -> 0 | N75: =N71 - N74 -> 0 | O75: =O71 - O74 -> 0 | P75: =P71 - P74 -> 0 | Q75: =Q71 - Q74 -> 0 | R75: =R71 - R74 -> 0 | ... AT75: =AT71 - AT74 -> 0
D77: Тело кредита | E77: руб | K77: =K75 -> 0 | L77: =K77 - L78 + L75 -> 1.6011026e+08 | M77: =L77 - M78 + M75 -> 1.5253371e+08 | N77: =M77 - N78 + N75 -> 1.4418266e+08 | O77: =N77 - O78 + O75 -> 1.3072521e+08 | P77: =O77 - P78 + P75 -> 1.0770906e+08 | Q77: =P77 - Q78 + Q75 -> 84459645 | R77: =Q77 - R78 + R75 -> 55815806 | S77: =R77 - S78 + S75 -> 29765799 | ... AT77: =AS77 - AT78 + AT75 -> 0
D78: Погашение тела | E78: руб | K78: =MIN(J77, SUM(K63, K74:K75)) -> 0 | L78: =MIN(K77, SUM(L63, L74:L75)) -> 0 | M78: =MIN(L77, SUM(M63, M74:M75)) -> 7576544.1 | N78: =MIN(M77, SUM(N63, N74:N75)) -> 8351051.2 | O78: =MIN(N77, SUM(O63, O74:O75)) -> 13457451 | P78: =MIN(O77, SUM(P63, P74:P75)) -> 23016153 | Q78: =MIN(P77, SUM(Q63, Q74:Q75)) -> 23249411 | R78: =MIN(Q77, SUM(R63, R74:R75)) -> 28643839 | ... AT78: =MIN(AS77, SUM(AT63, AT74:AT75)) -> 0
D79: Проценты к уплате | E79: руб | H79: ='Assumptions and inputs'!H108 -> 0.1 | L79: =K77 * $H$79 * L8 -> 0 | M79: =L77 * $H$79 * M8 -> 1359840.5 | N79: =M77 * $H$79 * N8 -> 1253701.7 | O79: =N77 * $H$79 * O8 -> 1224565.1 | P79: =O77 * $H$79 * P8 -> 1074453.8 | Q79: =P77 * $H$79 * Q8 -> 914789.24 | R79: =Q77 * $H$79 * R8 -> 717328.49 | S79: =R77 * $H$79 * S8 -> 458760.05 | ... AT79: =AS77 * $H$79 * AT8 -> 0
D81: =D31 -> Результат операционной деятельности | K81: =K82 - K83 - K87 - K88 - K89 -> 0 | L81: =L82 - L83 - L87 - L88 - L89 -> -45441022 | M81: =M82 - M83 - M87 - M88 - M89 -> 6216703.6 | N81: =N82 - N83 - N87 - N88 - N89 -> 7097349.5 | O81: =O82 - O83 - O87 - O88 - O89 -> 12232885 | P81: =P82 - P83 - P87 - P88 - P89 -> 22756111 | Q81: =Q82 - Q83 - Q87 - Q88 - Q89 -> 22685681 | R81: =R82 - R83 - R87 - R88 - R89 -> 28069977 | ... AT81: =AT82 - AT83 - AT87 - AT88 - AT89 -> 38357820
D82: =D32 -> Денежные поступления от операционной деятельности | E82: =E32 -> руб | K82: =K32 -> 0 | L82: =L32 -> 0 | M82: =M32 -> 81412917 | N82: =N32 -> 95808511 | O82: =O32 -> 1.1377725e+08 | P82: =P32 -> 1.2875614e+08 | Q82: =Q32 -> 1.3031604e+08 | R82: =R32 -> 1.2979296e+08 | ... AT82: =AT32 -> 2.5110565e+08
D83: =D33 -> Платежи по операционной деятельности | E83: =E33 -> руб | K83: =K33 -> 0 | L83: =L33 -> 45441022 | M83: =M33 -> 73836372 | N83: =N33 -> 87457460 | O83: =O33 -> 1.0031979e+08 | P83: =P33 -> 1.0492558e+08 | Q83: =Q33 -> 1.0502359e+08 | R83: =R33 -> 99122609 | ... AT83: =AT33 -> 1.9763303e+08
D84: =D34 -> Себестоимость производства | E84: =E34 -> руб | K84: =K34 -> 0 | L84: =L34 -> 45441022 | M84: =M34 -> 53483143 | N84: =N34 -> 63505332 | O84: =O34 -> 71875484 | P84: =P34 -> 72736540 | Q84: =Q34 -> 72444580 | R84: =R34 -> 66674371 | ... AT84: =AT34 -> 1.3485662e+08
D85: =D35 -> Маркетинг | E85: =E35 -> руб | F85: Процент от выручки | K85: =K35 -> 0 | L85: =L35 -> 0 | M85: =M35 -> 12211937 | N85: =N35 -> 14371277 | O85: =O35 -> 17066587 | P85: =P35 -> 19313421 | Q85: =Q35 -> 19547405 | R85: =R35 -> 19468943 | ... AT85: =AT35 -> 37665847
D86: =D36 -> АУП и непредвиденные затраты | E86: =E36 -> руб | F86: Процент от выручки | K86: =K36 -> 0 | L86: =L36 -> 0 | M86: =M36 -> 8141291.7 | N86: =N36 -> 9580851.1 | O86: =O36 -> 11377725 | P86: =P36 -> 12875614 | Q86: =Q36 -> 13031604 | R86: =R36 -> 12979296 | ... AT86: =AT36 -> 25110565
D87: =D79 -> Проценты к уплате | E87: руб | K87: =K79 -> 0 | L87: =L79 -> 0 | M87: =M79 -> 1359840.5 | N87: =N79 -> 1253701.7 | O87: =O79 -> 1224565.1 | P87: =P79 -> 1074453.8 | Q87: =Q79 -> 914789.24 | R87: =R79 -> 717328.49 | ... AT87: =AT79 -> 0
D88: =D37 -> Налог на прибыль | E88: руб | K88: ='P&L'!K55 -> 0 | L88: ='P&L'!L55 -> 0 | M88: ='P&L'!M55 -> 0 | N88: ='P&L'!N55 -> 0 | O88: ='P&L'!O55 -> 0 | P88: ='P&L'!P55 -> 0 | Q88: ='P&L'!Q55 -> 1691977.3 | R88: ='P&L'!R55 -> 1883040.9 | ... AT88: ='P&L'!AT55 -> 6202697.3
D89: =D38 -> НДС | E89: руб | K89: =K38 -> 0 | L89: =L38 -> 0 | M89: =M38 -> 0 | N89: =N38 -> 0 | O89: =O38 -> 0 | P89: =P38 -> 0 | Q89: =Q38 -> 0 | R89: =R38 -> 0 | ... AT89: =AT38 -> 8912103.4
D91: =D48 -> Результаты инвестиционной деятельности | K91: =K48 -> 297500000 | L91: =L48 -> 297500000 | M91: =M48 -> 0 | N91: =N48 -> 0 | O91: =O48 -> 0 | P91: =P48 -> 0 | Q91: =Q48 -> 0 | R91: =R48 -> 0 | ... AT91: =AT48 -> 0
D92: =D49 -> Процессное оборудование | K92: =K49 -> 152500000 | L92: =L49 -> 152500000 | M92: =M49 -> 0 | N92: =N49 -> 0 | O92: =O49 -> 0 | P92: =P49 -> 0 | Q92: =Q49 -> 0 | R92: =R49 -> 0 | ... AT92: =AT49 -> 0
D93: =D50 -> Приемка сырья | E93: =E50 -> руб. | K93: =K50 -> 45000000 | L93: =L50 -> 45000000 | M93: =M50 -> 0 | N93: =N50 -> 0 | O93: =O50 -> 0 | P93: =P50 -> 0 | Q93: =Q50 -> 0 | R93: =R50 -> 0 | ... AT93: =AT50 -> 0
D94: =D51 -> Миксинг | E94: =E51 -> руб. | K94: =K51 -> 35000000 | L94: =L51 -> 35000000 | M94: =M51 -> 0 | N94: =N51 -> 0 | O94: =O51 -> 0 | P94: =P51 -> 0 | Q94: =Q51 -> 0 | R94: =R51 -> 0 | ... AT94: =AT51 -> 0
D95: =D52 -> Декантация и деактивация | E95: =E52 -> руб. | K95: =K52 -> 27500000 | L95: =L52 -> 27500000 | M95: =M52 -> 0 | N95: =N52 -> 0 | O95: =O52 -> 0 | P95: =P52 -> 0 | Q95: =Q52 -> 0 | R95: =R52 -> 0 | ... AT95: =AT52 -> 0
D96: =D53 -> Гомогенизация и стерилизация | E96: =E53 -> руб. | K96: =K53 -> 45000000 | L96: =L53 -> 45000000 | M96: =M53 -> 0 | N96: =N53 -> 0 | O96: =O53 -> 0 | P96: =P53 -> 0 | Q96: =Q53 -> 0 | R96: =R53 -> 0 | ... AT96: =AT53 -> 0
D97: =D54 -> Упаковочная линия | K97: =K54 -> 55000000 | L97: =L54 -> 55000000 | M97: =M54 -> 0 | N97: =N54 -> 0 | O97: =O54 -> 0 | P97: =P54 -> 0 | Q97: =Q54 -> 0 | R97: =R54 -> 0 | ... AT97: =AT54 -> 0
D98: =D55 -> Фасовка | E98: =E55 -> руб. | K98: =K55 -> 35000000 | L98: =L55 -> 35000000 | M98: =M55 -> 0 | N98: =N55 -> 0 | O98: =O55 -> 0 | P98: =P55 -> 0 | Q98: =Q55 -> 0 | R98: =R55 -> 0 | ... AT98: =AT55 -> 0
D99: =D56 -> Группировка | E99: =E56 -> руб. | K99: =K56 -> 20000000 | L99: =L56 -> 20000000 | M99: =M56 -> 0 | N99: =N56 -> 0 | O99: =O56 -> 0 | P99: =P56 -> 0 | Q99: =Q56 -> 0 | R99: =R56 -> 0 | ... AT99: =AT56 -> 0
D100: =D57 -> Работа над технологией | E100: =E57 -> руб. | K100: =K57 -> 90000000 | L100: =L57 -> 90000000 | M100: =M57 -> 0 | N100: =N57 -> 0 | O100: =O57 -> 0 | P100: =P57 -> 0 | Q100: =Q57 -> 0 | R100: =R57 -> 0 | ... AT100: =AT57 -> 0
D102: Результаты финансовой деятельности | E102: руб | K102: =K103 - K104 -> 0 | L102: =L103 - L104 -> 1.6011026e+08 | M102: =M103 - M104 -> -7576544.1 | N102: =N103 - N104 -> -8351051.2 | O102: =O103 - O104 -> -13457451 | P102: =P103 - P104 -> -23016153 | Q102: =Q103 - Q104 -> -23249411 | R102: =R103 - R104 -> -28643839 | ... AT102: =AT103 - AT104 -> 0
D103: Привлеченные займы и кредиты | K103: =K75 -> 0 | L103: =L75 -> 1.6011026e+08 | M103: =M75 -> 0 | N103: =N75 -> 0 | O103: =O75 -> 0 | P103: =P75 -> 0 | Q103: =Q75 -> 0 | R103: =R75 -> 0 | ... AT103: =AT75 -> 0
D104: Погашение кредитов и займов | K104: =K78 -> 0 | L104: =L78 -> 0 | M104: =M78 -> 7576544.1 | N104: =N78 -> 8351051.2 | O104: =O78 -> 13457451 | P104: =P78 -> 23016153 | Q104: =Q78 -> 23249411 | R104: =R78 -> 28643839 | ... AT104: =AT78 -> 0
D106: Свободный денежный поток на акционерный капитал (FCFE) | H106: =SUM(K106:AT106) -> 4.3057677e+08 | K106: =K81 - K91 + K102 -> -297500000 | L106: =L81 - L91 + L102 -> -1.8283077e+08 | M106: =M81 - M91 + M102 -> -1359840.5 | N106: =N81 - N91 + N102 -> -1253701.7 | O106: =O81 - O91 + O102 -> -1224565.1 | P106: =P81 - P91 + P102 -> -260042.57 | Q106: =Q81 - Q91 + Q102 -> -563730.39 | R106: =R81 - R91 + R102 -> -573862.79 | ... AT106: =AT81 - AT91 + AT102 -> 38357820
D107: Ставка дисконта (COE) | E107: % | H107: ='Assumptions and inputs'!H99 -> 0.13001309
D108: Ежемесячная ставка дисконта | E108: % | H108: =(1 + H107) ^ (1 / 12) - 1 -> 0.01023782
D109: Дисконтированный денежный поток (Cost of Equity) | E109: руб | H109: =SUM(K109:AT109) -> 2.2788065e+08 | K109: =K106 / (1 + $H$108) ^ K7 -> -2.9448511e+08 | L109: =L106 / (1 + $H$108) ^ L7 -> -1.791439e+08 | M109: =M106 / (1 + $H$108) ^ M7 -> -1318915.9 | N109: =N106 / (1 + $H$108) ^ N7 -> -1203648.7 | O109: =O106 / (1 + $H$108) ^ O7 -> -1163760.9 | P109: =P106 / (1 + $H$108) ^ P7 -> -244626.05 | Q109: =Q106 / (1 + $H$108) ^ Q7 -> -524935.67 | R109: =R106 / (1 + $H$108) ^ R7 -> -528955.44 | ... AT109: =AT106 / (1 + $H$108) ^ AT7 -> 26582969
D111: Справочно расчет ДС на счете | E111: руб. | K111: =MAX(K106 + J111, 0) -> 0 | L111: =MAX(L106 + K111, 0) -> 0 | M111: =MAX(M106 + L111, 0) -> 0 | N111: =MAX(N106 + M111, 0) -> 0 | O111: =MAX(O106 + N111, 0) -> 0 | P111: =MAX(P106 + O111, 0) -> 0 | Q111: =MAX(Q106 + P111, 0) -> 0 | R111: =MAX(R106 + Q111, 0) -> 0 | ... AT111: =MAX(AT106 + AS111, 0) -> 9.1671253e+08

Sheet P&L
D1: ToolKit Финансы. Блок Финансовое моделирование. P&L
D3: Временные шкалы
E4: Ед.изм. | F4: Комментарий | G4: Проверка | H4: Фикс.значения * | I4: База * | K4: =YEAR(K5) -> 2029 | L4: =YEAR(L5) -> 2029 | M4: =YEAR(M5) -> 2029 | N4: =YEAR(N5) -> 2029 | O4: =YEAR(O5) -> 2029 | P4: =YEAR(P5) -> 2029 | Q4: =YEAR(Q5) -> 2029 | R4: =YEAR(R5) -> 2029 | ... AT4: =YEAR(AT5) -> 2031
D5: Начало периода | E5: дата | K5: =I6 + 1 -> 47119 | L5: =K6 + 1 -> 47150 | M5: =L6 + 1 -> 47178 | N5: =M6 + 1 -> 47209 | O5: =N6 + 1 -> 47239 | P5: =O6 + 1 -> 47270 | Q5: =P6 + 1 -> 47300 | R5: =Q6 + 1 -> 47331 | S5: =R6 + 1 -> 47362 | ... AT5: =AS6 + 1 -> 48183
D6: Конец периода | E6: дата | I6: ='Assumptions and inputs'!I8 -> 47118 | K6: =EOMONTH(K5, 0) -> 47149 | L6: =EOMONTH(L5, 0) -> 47177 | M6: =EOMONTH(M5, 0) -> 47208 | N6: =EOMONTH(N5, 0) -> 47238 | O6: =EOMONTH(O5, 0) -> 47269 | P6: =EOMONTH(P5, 0) -> 47299 | Q6: =EOMONTH(Q5, 0) -> 47330 | R6: =EOMONTH(R5, 0) -> 47361 | ... AT6: =EOMONTH(AT5, 0) -> 48213
D7: Номер периода | I7: 0 | K7: =I7 + 1 -> 1 | L7: =K7 + 1 -> 2 | M7: =L7 + 1 -> 3 | N7: =M7 + 1 -> 4 | O7: =N7 + 1 -> 5 | P7: =O7 + 1 -> 6 | Q7: =P7 + 1 -> 7 | R7: =Q7 + 1 -> 8 | S7: =R7 + 1 -> 9 | ... AT7: =AS7 + 1 -> 36
D8: Длина периода | K8: =(K6 - K5 + 1)/ (DATE(YEAR(K6), 12, 31) - DATE(YEAR(K6), 1, 1) + 1) -> 0.084931507 | L8: =(L6 - L5 + 1)/ (DATE(YEAR(L6), 12, 31) - DATE(YEAR(L6), 1, 1) + 1) -> 0.076712329 | M8: =(M6 - M5 + 1)/ (DATE(YEAR(M6), 12, 31) - DATE(YEAR(M6), 1, 1) + 1) -> 0.084931507 | N8: =(N6 - N5 + 1)/ (DATE(YEAR(N6), 12, 31) - DATE(YEAR(N6), 1, 1) + 1) -> 0.082191781 | O8: =(O6 - O5 + 1)/ (DATE(YEAR(O6), 12, 31) - DATE(YEAR(O6), 1, 1) + 1) -> 0.084931507 | P8: =(P6 - P5 + 1)/ (DATE(YEAR(P6), 12, 31) - DATE(YEAR(P6), 1, 1) + 1) -> 0.082191781 | Q8: =(Q6 - Q5 + 1)/ (DATE(YEAR(Q6), 12, 31) - DATE(YEAR(Q6), 1, 1) + 1) -> 0.084931507 | R8: =(R6 - R5 + 1)/ (DATE(YEAR(R6), 12, 31) - DATE(YEAR(R6), 1, 1) + 1) -> 0.084931507 | ... AT8: =(AT6 - AT5 + 1)/ (DATE(YEAR(AT6), 12, 31) - DATE(YEAR(AT6), 1, 1) + 1) -> 0.084931507
D10: Шаг 1. Перенесите необходимые для расчета показателей данные на рабочий лист
D12: =CF!D15 -> Объем продаж и цены реализации
D13: =CF!D16 -> Продажи | E13: =CF!E16 -> кг | K13: =CF!K16 -> 0 | L13: =CF!L16 -> 0 | M13: =CF!M16 -> 326027.4 | N13: =CF!N16 -> 382191.78 | O13: =CF!O16 -> 452054.79 | P13: =CF!P16 -> 509589.04 | Q13: =CF!Q16 -> 513698.63 | R13: =CF!R16 -> 509589.04 | ... AT13: =CF!AT16 -> 901232.88
D14: =CF!D17 -> Динамика цен (вкл. НДС) | E14: =CF!E17 -> руб | I14: =CF!I17 -> 247.81649 | K14: =CF!K17 -> 247.81649 | L14: =CF!L17 -> 248.71251 | M14: =CF!M17 -> 249.71189 | N14: =CF!N17 -> 250.68177 | O14: =CF!O17 -> 251.68906 | P14: =CF!P17 -> 252.66662 | Q14: =CF!Q17 -> 253.68188 | R14: =CF!R17 -> 254.70123 | ... AT14: =CF!AT17 -> 278.6246
D16: =CF!D19 -> График производства
D17: =CF!D20 -> Себестоимость | E17: =CF!E20 -> руб | K17: =CF!K20 -> 138.32 | L17: =CF!L20 -> 138.32 | M17: =CF!M20 -> 138.32 | N17: =CF!N20 -> 138.32 | O17: =CF!O20 -> 138.32 | P17: =CF!P20 -> 138.32 | Q17: =CF!Q20 -> 138.32 | R17: =CF!R20 -> 138.32 | ... AT17: =CF!AT20 -> 136.29907
D18: =CF!D21 -> Себестоимость с учетом инфляции | E18: =CF!E21 -> руб | K18: =CF!K21 -> 138.32 | L18: =CF!L21 -> 139.37792 | M18: =CF!M21 -> 139.93797 | N18: =CF!N21 -> 140.48149 | O18: =CF!O21 -> 141.04598 | P18: =CF!P21 -> 141.5938 | Q18: =CF!Q21 -> 142.16275 | R18: =CF!R21 -> 142.73399 | ... AT18: =CF!AT21 -> 153.85929
D19: =CF!D22 -> График производства | E19: =CF!E22 -> кг | F19: Не используется в отчете | K19: =CF!K22 -> 0 | L19: =CF!L22 -> 326027.4 | M19: =CF!M22 -> 382191.78 | N19: =CF!N22 -> 452054.79 | O19: =CF!O22 -> 509589.04 | P19: =CF!P22 -> 513698.63 | Q19: =CF!Q22 -> 509589.04 | R19: =CF!R22 -> 467123.29 | ... AT19: =CF!AT22 -> 876493.15
D21: ='Assumptions and inputs'!D21 -> Налог на прибыль | E21: ='Assumptions and inputs'!E21 -> % | H21: ='Assumptions and inputs'!H21 -> 0.2
D22: ='Assumptions and inputs'!D22 -> НДС | E22: ='Assumptions and inputs'!E22 -> % | H22: ='Assumptions and inputs'!H22 -> 0.2
D24: Шаг 2. На основе CF постройте отчет о прибылях и убытках без учета Tax shield
C26: Отчет о прибылях и убытках
C27: Выручка от продаж | E27: руб | F27: За вычетом НДС | K27: =CF!K32/(1+$H$22) -> 0 | L27: =CF!L32/(1+$H$22) -> 0 | M27: =CF!M32/(1+$H$22) -> 67844097 | N27: =CF!N32/(1+$H$22) -> 79840426 | O27: =CF!O32/(1+$H$22) -> 94814371 | P27: =CF!P32/(1+$H$22) -> 1.0729678e+08 | Q27: =CF!Q32/(1+$H$22) -> 1.085967e+08 | R27: =CF!R32/(1+$H$22) -> 1.081608e+08 | ... AT27: =CF!AT32/(1+$H$22) -> 2.0925471e+08
C28: Затратная часть | K28: =SUM(K29:K31) -> 0 | L28: =SUM(L29:L31) -> 0 | M28: =SUM(M29:M31) -> 54980702 | N28: =SUM(N29:N31) -> 64702500 | O28: =SUM(O29:O31) -> 76837351 | P28: =SUM(P29:P31) -> 86953069 | Q28: =SUM(Q29:Q31) -> 88006516 | R28: =SUM(R29:R31) -> 87653263 | ... AT28: =SUM(AT29:AT31) -> 1.6786622e+08
D29: Себестоимость производства | E29: руб | F29: За вычетом НДС | K29: =K18*K13/(1+$H$22) -> 0 | L29: =L18*L13/(1+$H$22) -> 0 | M29: =M18*M13/(1+$H$22) -> 38019678 | N29: =N18*N13/(1+$H$22) -> 44742393 | O29: =O18*O13/(1+$H$22) -> 53133758 | P29: =P18*P13/(1+$H$22) -> 60128873 | Q29: =Q18*Q13/(1+$H$22) -> 60857342 | R29: =R18*R13/(1+$H$22) -> 60613064 | ... AT29: =AT18*AT13/(1+$H$22) -> 1.1555254e+08
D30: ='Assumptions and inputs'!D88 -> Маркетинг | E30: руб | H30: ='Assumptions and inputs'!H88 -> 0.15 | K30: =K27*$H$30 -> 0 | L30: =L27*$H$30 -> 0 | M30: =M27*$H$30 -> 10176615 | N30: =N27*$H$30 -> 11976064 | O30: =O27*$H$30 -> 14222156 | P30: =P27*$H$30 -> 16094518 | Q30: =Q27*$H$30 -> 16289505 | R30: =R27*$H$30 -> 16224119 | ... AT30: =AT27*$H$30 -> 31388206
D31: ='Assumptions and inputs'!D89 -> АУП и непредвиденные затраты | E31: руб | H31: ='Assumptions and inputs'!H89 -> 0.1 | K31: =K27*$H$31 -> 0 | L31: =L27*$H$31 -> 0 | M31: =M27*$H$31 -> 6784409.7 | N31: =N27*$H$31 -> 7984042.6 | O31: =O27*$H$31 -> 9481437.1 | P31: =P27*$H$31 -> 10729678 | Q31: =Q27*$H$31 -> 10859670 | R31: =R27*$H$31 -> 10816080 | ... AT31: =AT27*$H$31 -> 20925471
C32: EBITDA | E32: руб | K32: =K27-K28 -> 0 | L32: =L27-L28 -> 0 | M32: =M27-M28 -> 12863395 | N32: =N27-N28 -> 15137926 | O32: =O27-O28 -> 17977020 | P32: =P27-P28 -> 20343714 | Q32: =Q27-Q28 -> 20590181 | R32: =R27-R28 -> 20507533 | ... AT32: =AT27-AT28 -> 41388486
D33: Амортизация | E33: руб | K33: ='Assumptions and inputs'!K94 -> 10375000 | L33: ='Assumptions and inputs'!L94 -> 10375000 | M33: ='Assumptions and inputs'!M94 -> 10375000 | N33: ='Assumptions and inputs'!N94 -> 10375000 | O33: ='Assumptions and inputs'!O94 -> 10375000 | P33: ='Assumptions and inputs'!P94 -> 10375000 | Q33: ='Assumptions and inputs'!Q94 -> 10375000 | R33: ='Assumptions and inputs'!R94 -> 10375000 | ... AT33: ='Assumptions and inputs'!AT94 -> 10375000
C34: Операционная прибыль проекта | E34: руб | K34: =K32-K33 -> -10375000 | L34: =L32-L33 -> -10375000 | M34: =M32-M33 -> 2488395.1 | N34: =N32-N33 -> 4762926.4 | O34: =O32-O33 -> 7602020.4 | P34: =P32-P33 -> 9968714.2 | Q34: =Q32-Q33 -> 10215181 | R34: =R32-R33 -> 10132533 | ... AT34: =AT32-AT33 -> 31013486
C35: Налоговая база по налогу на прибыль (EBT) | E35: руб | K35: =K34 -> -10375000 | L35: =L34 -> -10375000 | M35: =M34 -> 2488395.1 | N35: =N34 -> 4762926.4 | O35: =O34 -> 7602020.4 | P35: =P34 -> 9968714.2 | Q35: =Q34 -> 10215181 | R35: =R34 -> 10132533 | ... AT35: =AT34 -> 31013486
D36: Налоговая база накопительным итогом | E36: руб | K36: =K35 -> -10375000 | L36: =K36+L35 -> -20750000 | M36: =L36+M35 -> -18261605 | N36: =M36+N35 -> -13498679 | O36: =N36+O35 -> -5896658.1 | P36: =O36+P35 -> 4072056 | Q36: =P36+Q35 -> 14287237 | R36: =Q36+R35 -> 24419770 | S36: =R36+S35 -> 32916355 | ... AT36: =AS36+AT35 -> 8.2643212e+08
D37: Налог на прибыль | E37: руб | L37: =IF(AND(L36>0,K36<0),L36*$H$21,IF(L36>0,L35*$H$21,0))*IF(L35<0,0,1) -> 0 | M37: =IF(AND(M36>0,L36<0),M36*$H$21,IF(M36>0,M35*$H$21,0))*IF(M35<0,0,1) -> 0 | N37: =IF(AND(N36>0,M36<0),N36*$H$21,IF(N36>0,N35*$H$21,0))*IF(N35<0,0,1) -> 0 | O37: =IF(AND(O36>0,N36<0),O36*$H$21,IF(O36>0,O35*$H$21,0))*IF(O35<0,0,1) -> 0 | P37: =IF(AND(P36>0,O36<0),P36*$H$21,IF(P36>0,P35*$H$21,0))*IF(P35<0,0,1) -> 814411.21 | Q37: =IF(AND(Q36>0,P36<0),Q36*$H$21,IF(Q36>0,Q35*$H$21,0))*IF(Q35<0,0,1) -> 2043036.1 | R37: =IF(AND(R36>0,Q36<0),R36*$H$21,IF(R36>0,R35*$H$21,0))*IF(R35<0,0,1) -> 2026506.6 | S37: =IF(AND(S36>0,R36<0),S36*$H$21,IF(S36>0,S35*$H$21,0))*IF(S35<0,0,1) -> 1699317.1 | ... AT37: =IF(AND(AT36>0,AS36<0),AT36*$H$21,IF(AT36>0,AT35*$H$21,0))*IF(AT35<0,0,1) -> 6202697.3
C39: Чистая прибыль проекта | K39: =K35-K37 -> -10375000 | L39: =L35-L37 -> -10375000 | M39: =M35-M37 -> 2488395.1 | N39: =N35-N37 -> 4762926.4 | O39: =O35-O37 -> 7602020.4 | P39: =P35-P37 -> 9154302.9 | Q39: =Q35-Q37 -> 8172144.6 | R39: =R35-R37 -> 8106026.3 | ... AT39: =AT35-AT37 -> 24810789
D41: Шаг 3. На основе CF постройте отчет о прибылях и убытках c учетом Tax shield
C43: Отчет о прибылях и убытках
C44: Выручка от продаж | E44: руб | F44: За вычетом НДС | K44: =K27 -> 0 | L44: =L27 -> 0 | M44: =M27 -> 67844097 | N44: =N27 -> 79840426 | O44: =O27 -> 94814371 | P44: =P27 -> 1.0729678e+08 | Q44: =Q27 -> 1.085967e+08 | R44: =R27 -> 1.081608e+08 | ... AT44: =AT27 -> 2.0925471e+08
C45: Затратная часть | K45: =K28 -> 0 | L45: =L28 -> 0 | M45: =M28 -> 54980702 | N45: =N28 -> 64702500 | O45: =O28 -> 76837351 | P45: =P28 -> 86953069 | Q45: =Q28 -> 88006516 | R45: =R28 -> 87653263 | ... AT45: =AT28 -> 1.6786622e+08
D46: Себестоимость производства | E46: руб | F46: За вычетом НДС | K46: =K29 -> 0 | L46: =L29 -> 0 | M46: =M29 -> 38019678 | N46: =N29 -> 44742393 | O46: =O29 -> 53133758 | P46: =P29 -> 60128873 | Q46: =Q29 -> 60857342 | R46: =R29 -> 60613064 | ... AT46: =AT29 -> 1.1555254e+08
D47: Маркетинг | E47: руб | K47: =K30 -> 0 | L47: =L30 -> 0 | M47: =M30 -> 10176615 | N47: =N30 -> 11976064 | O47: =O30 -> 14222156 | P47: =P30 -> 16094518 | Q47: =Q30 -> 16289505 | R47: =R30 -> 16224119 | ... AT47: =AT30 -> 31388206
D48: АУП и непредвиденные затраты | E48: руб | K48: =K31 -> 0 | L48: =L31 -> 0 | M48: =M31 -> 6784409.7 | N48: =N31 -> 7984042.6 | O48: =O31 -> 9481437.1 | P48: =P31 -> 10729678 | Q48: =Q31 -> 10859670 | R48: =R31 -> 10816080 | ... AT48: =AT31 -> 20925471
C49: EBITDA | E49: руб | K49: =K44-K45 -> 0 | L49: =L44-L45 -> 0 | M49: =M44-M45 -> 12863395 | N49: =N44-N45 -> 15137926 | O49: =O44-O45 -> 17977020 | P49: =P44-P45 -> 20343714 | Q49: =Q44-Q45 -> 20590181 | R49: =R44-R45 -> 20507533 | ... AT49: =AT44-AT45 -> 41388486
D50: Амортизация | E50: руб | K50: =K33 -> 10375000 | L50: =L33 -> 10375000 | M50: =M33 -> 10375000 | N50: =N33 -> 10375000 | O50: =O33 -> 10375000 | P50: =P33 -> 10375000 | Q50: =Q33 -> 10375000 | R50: =R33 -> 10375000 | ... AT50: =AT33 -> 10375000
D51: Проценты начисленные | E51: руб | K51: =CF!K79 -> 0 | L51: =CF!L79 -> 0 | M51: =CF!M79 -> 1359840.5 | N51: =CF!N79 -> 1253701.7 | O51: =CF!O79 -> 1224565.1 | P51: =CF!P79 -> 1074453.8 | Q51: =CF!Q79 -> 914789.24 | R51: =CF!R79 -> 717328.49 | ... AT51: =CF!AT79 -> 0
C52: Операционная прибыль проекта | E52: руб | K52: =K49 - K50 - K51 -> -10375000 | L52: =L49 - L50 - L51 -> -10375000 | M52: =M49 - M50 - M51 -> 1128554.6 | N52: =N49 - N50 - N51 -> 3509224.6 | O52: =O49 - O50 - O51 -> 6377455.4 | P52: =P49 - P50 - P51 -> 8894260.4 | Q52: =Q49 - Q50 - Q51 -> 9300391.5 | R52: =R49 - R50 - R51 -> 9415204.4 | ... AT52: =AT49 - AT50 - AT51 -> 31013486
C53: Налоговая база по налогу на прибыль (EBT) | E53: руб | K53: =K52 -> -10375000 | L53: =L52 -> -10375000 | M53: =M52 -> 1128554.6 | N53: =N52 -> 3509224.6 | O53: =O52 -> 6377455.4 | P53: =P52 -> 8894260.4 | Q53: =Q52 -> 9300391.5 | R53: =R52 -> 9415204.4 | ... AT53: =AT52 -> 31013486
D54: Налоговая база накопительным итогом | E54: руб | K54: =K53 -> -10375000 | L54: =K54+L53 -> -20750000 | M54: =L54+M53 -> -19621445 | N54: =M54+N53 -> -16112221 | O54: =N54+O53 -> -9734765.4 | P54: =O54+P53 -> -840505.05 | Q54: =P54+Q53 -> 8459886.5 | R54: =Q54+R53 -> 17875091 | S54: =R54+S53 -> 25912916 | ... AT54: =AS54+AT53 -> 8.1883771e+08
D55: Налог на прибыль (с учетом Tax Shield) | E55: руб | L55: =IF(AND(L54>0,K54<0),L54*$H$21,IF(L54>0,L53*$H$21,0))*IF(L53<0,0,1) -> 0 | M55: =IF(AND(M54>0,L54<0),M54*$H$21,IF(M54>0,M53*$H$21,0))*IF(M53<0,0,1) -> 0 | N55: =IF(AND(N54>0,M54<0),N54*$H$21,IF(N54>0,N53*$H$21,0))*IF(N53<0,0,1) -> 0 | O55: =IF(AND(O54>0,N54<0),O54*$H$21,IF(O54>0,O53*$H$21,0))*IF(O53<0,0,1) -> 0 | P55: =IF(AND(P54>0,O54<0),P54*$H$21,IF(P54>0,P53*$H$21,0))*IF(P53<0,0,1) -> 0 | Q55: =IF(AND(Q54>0,P54<0),Q54*$H$21,IF(Q54>0,Q53*$H$21,0))*IF(Q53<0,0,1) -> 1691977.3 | R55: =IF(AND(R54>0,Q54<0),R54*$H$21,IF(R54>0,R53*$H$21,0))*IF(R53<0,0,1) -> 1883040.9 | S55: =IF(AND(S54>0,R54<0),S54*$H$21,IF(S54>0,S53*$H$21,0))*IF(S53<0,0,1) -> 1607565.1 | ... AT55: =IF(AND(AT54>0,AS54<0),AT54*$H$21,IF(AT54>0,AT53*$H$21,0))*IF(AT53<0,0,1) -> 6202697.3
C57: Чистая прибыль проекта | K57: =K53-K55 -> -10375000 | L57: =L53-L55 -> -10375000 | M57: =M53-M55 -> 1128554.6 | N57: =N53-N55 -> 3509224.6 | O57: =O53-O55 -> 6377455.4 | P57: =P53-P55 -> 8894260.4 | Q57: =Q53-Q55 -> 7608414.2 | R57: =R53-R55 -> 7532163.5 | ... AT57: =AT53-AT55 -> 24810789

Sheet Показатели
D1: ToolKit Финансы. Блок Финансовое моделирование. Показатели эффективности
C3: Временные шкалы
E4: Ед.изм. | F4: Комментарий | G4: Проверка | H4: Фикс.значения * | I4: База * | K4: =YEAR(K5) -> 2029 | L4: =YEAR(L5) -> 2029 | M4: =YEAR(M5) -> 2029 | N4: =YEAR(N5) -> 2029 | O4: =YEAR(O5) -> 2029 | P4: =YEAR(P5) -> 2029 | Q4: =YEAR(Q5) -> 2029 | R4: =YEAR(R5) -> 2029 | ... AT4: =YEAR(AT5) -> 2031
D5: Начало периода | E5: дата | K5: =I6 + 1 -> 47119 | L5: =K6 + 1 -> 47150 | M5: =L6 + 1 -> 47178 | N5: =M6 + 1 -> 47209 | O5: =N6 + 1 -> 47239 | P5: =O6 + 1 -> 47270 | Q5: =P6 + 1 -> 47300 | R5: =Q6 + 1 -> 47331 | S5: =R6 + 1 -> 47362 | ... AT5: =AS6 + 1 -> 48183
D6: Конец периода | E6: дата | I6: ='Assumptions and inputs'!I8 -> 47118 | K6: =EOMONTH(K5, 0) -> 47149 | L6: =EOMONTH(L5, 0) -> 47177 | M6: =EOMONTH(M5, 0) -> 47208 | N6: =EOMONTH(N5, 0) -> 47238 | O6: =EOMONTH(O5, 0) -> 47269 | P6: =EOMONTH(P5, 0) -> 47299 | Q6: =EOMONTH(Q5, 0) -> 47330 | R6: =EOMONTH(R5, 0) -> 47361 | ... AT6: =EOMONTH(AT5, 0) -> 48213
D7: Номер периода | I7: ='Assumptions and inputs'!I9 -> 0 | K7: =I7 + 1 -> 1 | L7: =K7 + 1 -> 2 | M7: =L7 + 1 -> 3 | N7: =M7 + 1 -> 4 | O7: =N7 + 1 -> 5 | P7: =O7 + 1 -> 6 | Q7: =P7 + 1 -> 7 | R7: =Q7 + 1 -> 8 | S7: =R7 + 1 -> 9 | ... AT7: =AS7 + 1 -> 36
D8: Длина периода | K8: =(K6 - K5 + 1)/ (DATE(YEAR(K6), 12, 31) - DATE(YEAR(K6), 1, 1) + 1) -> 0.084931507 | L8: =(L6 - L5 + 1)/ (DATE(YEAR(L6), 12, 31) - DATE(YEAR(L6), 1, 1) + 1) -> 0.076712329 | M8: =(M6 - M5 + 1)/ (DATE(YEAR(M6), 12, 31) - DATE(YEAR(M6), 1, 1) + 1) -> 0.084931507 | N8: =(N6 - N5 + 1)/ (DATE(YEAR(N6), 12, 31) - DATE(YEAR(N6), 1, 1) + 1) -> 0.082191781 | O8: =(O6 - O5 + 1)/ (DATE(YEAR(O6), 12, 31) - DATE(YEAR(O6), 1, 1) + 1) -> 0.084931507 | P8: =(P6 - P5 + 1)/ (DATE(YEAR(P6), 12, 31) - DATE(YEAR(P6), 1, 1) + 1) -> 0.082191781 | Q8: =(Q6 - Q5 + 1)/ (DATE(YEAR(Q6), 12, 31) - DATE(YEAR(Q6), 1, 1) + 1) -> 0.084931507 | R8: =(R6 - R5 + 1)/ (DATE(YEAR(R6), 12, 31) - DATE(YEAR(R6), 1, 1) + 1) -> 0.084931507 | ... AT8: =(AT6 - AT5 + 1)/ (DATE(YEAR(AT6), 12, 31) - DATE(YEAR(AT6), 1, 1) + 1) -> 0.084931507
D10: Шаг 1. Перенесите необходимые для расчета показателей данные на рабочий лист
D12: =CF!D63 -> Cвободный денежный поток на фирму (FCFF) | K12: =CF!K63 -> -297500000 | L12: =CF!L63 -> -3.4294102e+08 | M12: =CF!M63 -> 7576544.1 | N12: =CF!N63 -> 8351051.2 | O12: =CF!O63 -> 13457451 | P12: =CF!P63 -> 23016153 | Q12: =CF!Q63 -> 23249411 | R12: =CF!R63 -> 28643839 | ... AT12: =CF!AT63 -> 38357820
D13: =CF!D66 -> Дисконтированный денежный поток (WACC) | K13: =CF!K66 -> -2.9475829e+08 | L13: =CF!L66 -> -3.3664917e+08 | M13: =CF!M66 -> 7368996 | N13: =CF!N66 -> 8047432.9 | O13: =CF!O66 -> 12848667 | P13: =CF!P66 -> 21772438 | Q13: =CF!Q66 -> 21790407 | R13: =CF!R66 -> 26598899 | ... AT13: =CF!AT66 -> 27485261
D15: =CF!D106 -> Свободный денежный поток на акционерный капитал (FCFE) | K15: =CF!K106 -> -297500000 | L15: =CF!L106 -> -1.8283077e+08 | M15: =CF!M106 -> -1359840.5 | N15: =CF!N106 -> -1253701.7 | O15: =CF!O106 -> -1224565.1 | P15: =CF!P106 -> -260042.57 | Q15: =CF!Q106 -> -563730.39 | R15: =CF!R106 -> -573862.79 | ... AT15: =CF!AT106 -> 38357820
D16: =CF!D109 -> Дисконтированный денежный поток (Cost of Equity) | K16: =CF!K109 -> -2.9448511e+08 | L16: =CF!L109 -> -1.791439e+08 | M16: =CF!M109 -> -1318915.9 | N16: =CF!N109 -> -1203648.7 | O16: =CF!O109 -> -1163760.9 | P16: =CF!P109 -> -244626.05 | Q16: =CF!Q109 -> -524935.67 | R16: =CF!R109 -> -528955.44 | ... AT16: =CF!AT109 -> 26582969
D18: Шаг 2. Рассчитайте окупаеммость для FCFF и FCFE
D19: FCFF
D20: Обыкновенный период окупаемости | E20: мес | H20: =SUM(K21:AT22) -> 25.539057 | K20: =SUM($K$12:K12) -> -297500000 | L20: =SUM($K$12:L12) -> -6.4044102e+08 | M20: =SUM($K$12:M12) -> -6.3286448e+08 | N20: =SUM($K$12:N12) -> -6.2451343e+08 | O20: =SUM($K$12:O12) -> -6.1105598e+08 | P20: =SUM($K$12:P12) -> -5.8803982e+08 | Q20: =SUM($K$12:Q12) -> -5.6479041e+08 | R20: =SUM($K$12:R12) -> -5.3614657e+08 | ... AT20: =SUM($K$12:AT12) -> 4.3665229e+08
K21: =IF(AND(J20<0,K20>0),-J20/K12,0) -> 0 | L21: =IF(AND(K20<0,L20>0),-K20/L12,0) -> 0 | M21: =IF(AND(L20<0,M20>0),-L20/M12,0) -> 0 | N21: =IF(AND(M20<0,N20>0),-M20/N12,0) -> 0 | O21: =IF(AND(N20<0,O20>0),-N20/O12,0) -> 0 | P21: =IF(AND(O20<0,P20>0),-O20/P12,0) -> 0 | Q21: =IF(AND(P20<0,Q20>0),-P20/Q12,0) -> 0 | R21: =IF(AND(Q20<0,R20>0),-Q20/R12,0) -> 0 | ... AT21: =IF(AND(AS20<0,AT20>0),-AS20/AT12,0) -> 0
K22: =IF(K20<0,1,0) -> 1 | L22: =IF(L20<0,1,0) -> 1 | M22: =IF(M20<0,1,0) -> 1 | N22: =IF(N20<0,1,0) -> 1 | O22: =IF(O20<0,1,0) -> 1 | P22: =IF(P20<0,1,0) -> 1 | Q22: =IF(Q20<0,1,0) -> 1 | R22: =IF(R20<0,1,0) -> 1 | ... AT22: =IF(AT20<0,1,0) -> 0
D24: Дисконтированный период окупаемости | E24: мес | H24: =SUM(K25:AT26) -> 29.832005 | K24: =SUM($K$13:K13) -> -2.9475829e+08 | L24: =SUM($K$13:L13) -> -6.3140746e+08 | M24: =SUM($K$13:M13) -> -6.2403846e+08 | N24: =SUM($K$13:N13) -> -6.1599103e+08 | O24: =SUM($K$13:O13) -> -6.0314236e+08 | P24: =SUM($K$13:P13) -> -5.8136992e+08 | Q24: =SUM($K$13:Q13) -> -5.5957952e+08 | R24: =SUM($K$13:R13) -> -5.3298062e+08 | ... AT24: =SUM($K$13:AT13) -> 2.4178628e+08
K25: =IF(AND(J24<0,K24>0),-J24/K13,0) -> 0 | L25: =IF(AND(K24<0,L24>0),-K24/L13,0) -> 0 | M25: =IF(AND(L24<0,M24>0),-L24/M13,0) -> 0 | N25: =IF(AND(M24<0,N24>0),-M24/N13,0) -> 0 | O25: =IF(AND(N24<0,O24>0),-N24/O13,0) -> 0 | P25: =IF(AND(O24<0,P24>0),-O24/P13,0) -> 0 | Q25: =IF(AND(P24<0,Q24>0),-P24/Q13,0) -> 0 | R25: =IF(AND(Q24<0,R24>0),-Q24/R13,0) -> 0 | ... AT25: =IF(AND(AS24<0,AT24>0),-AS24/AT13,0) -> 0
K26: =IF(K24<0,1,0) -> 1 | L26: =IF(L24<0,1,0) -> 1 | M26: =IF(M24<0,1,0) -> 1 | N26: =IF(N24<0,1,0) -> 1 | O26: =IF(O24<0,1,0) -> 1 | P26: =IF(P24<0,1,0) -> 1 | Q26: =IF(Q24<0,1,0) -> 1 | R26: =IF(R24<0,1,0) -> 1 | ... AT26: =IF(AT24<0,1,0) -> 0
D28: FCFE
D29: Обыкновенный период окупаемости | E29: мес | H29: =SUM(K30:AT31) -> 25.749247 | K29: =SUM($K$15:K15) -> -297500000 | L29: =SUM($K$15:L15) -> -4.8033077e+08 | M29: =SUM($K$15:M15) -> -4.8169061e+08 | N29: =SUM($K$15:N15) -> -4.8294431e+08 | O29: =SUM($K$15:O15) -> -4.8416887e+08 | P29: =SUM($K$15:P15) -> -4.8442892e+08 | Q29: =SUM($K$15:Q15) -> -4.8499265e+08 | R29: =SUM($K$15:R15) -> -4.8556651e+08 | ... AT29: =SUM($K$15:AT15) -> 4.3057677e+08
K30: =IF(AND(J29<0,K29>0),-J29/K15,0) -> 0 | L30: =IF(AND(K29<0,L29>0),-K29/L15,0) -> 0 | M30: =IF(AND(L29<0,M29>0),-L29/M15,0) -> 0 | N30: =IF(AND(M29<0,N29>0),-M29/N15,0) -> 0 | O30: =IF(AND(N29<0,O29>0),-N29/O15,0) -> 0 | P30: =IF(AND(O29<0,P29>0),-O29/P15,0) -> 0 | Q30: =IF(AND(P29<0,Q29>0),-P29/Q15,0) -> 0 | R30: =IF(AND(Q29<0,R29>0),-Q29/R15,0) -> 0 | ... AT30: =IF(AND(AS29<0,AT29>0),-AS29/AT15,0) -> 0
K31: =IF(K29<0,1,0) -> 1 | L31: =IF(L29<0,1,0) -> 1 | M31: =IF(M29<0,1,0) -> 1 | N31: =IF(N29<0,1,0) -> 1 | O31: =IF(O29<0,1,0) -> 1 | P31: =IF(P29<0,1,0) -> 1 | Q31: =IF(Q29<0,1,0) -> 1 | R31: =IF(R29<0,1,0) -> 1 | ... AT31: =IF(AT29<0,1,0) -> 0
D33: Дисконтированный период окупаемости | E33: мес | H33: =SUM(K34:AT35) -> 30.01624 | K33: =SUM($K$16:K16) -> -2.9448511e+08 | L33: =SUM($K$16:L16) -> -4.7362902e+08 | M33: =SUM($K$16:M16) -> -4.7494793e+08 | N33: =SUM($K$16:N16) -> -4.7615158e+08 | O33: =SUM($K$16:O16) -> -4.7731534e+08 | P33: =SUM($K$16:P16) -> -4.7755997e+08 | Q33: =SUM($K$16:Q16) -> -4.7808491e+08 | R33: =SUM($K$16:R16) -> -4.7861386e+08 | ... AT33: =SUM($K$16:AT16) -> 2.2788065e+08
K34: =IF(AND(J33<0,K33>0),-J33/K16,0) -> 0 | L34: =IF(AND(K33<0,L33>0),-K33/L16,0) -> 0 | M34: =IF(AND(L33<0,M33>0),-L33/M16,0) -> 0 | N34: =IF(AND(M33<0,N33>0),-M33/N16,0) -> 0 | O34: =IF(AND(N33<0,O33>0),-N33/O16,0) -> 0 | P34: =IF(AND(O33<0,P33>0),-O33/P16,0) -> 0 | Q34: =IF(AND(P33<0,Q33>0),-P33/Q16,0) -> 0 | R34: =IF(AND(Q33<0,R33>0),-Q33/R16,0) -> 0 | ... AT34: =IF(AND(AS33<0,AT33>0),-AS33/AT16,0) -> 0
K35: =IF(K33<0,1,0) -> 1 | L35: =IF(L33<0,1,0) -> 1 | M35: =IF(M33<0,1,0) -> 1 | N35: =IF(N33<0,1,0) -> 1 | O35: =IF(O33<0,1,0) -> 1 | P35: =IF(P33<0,1,0) -> 1 | Q35: =IF(Q33<0,1,0) -> 1 | R35: =IF(R33<0,1,0) -> 1 | ... AT35: =IF(AT33<0,1,0) -> 0
D36: Шаг 3. Определите внутреннюю норму доходности
D37: FCFF
D38: Внутренняя ставка доходности | E38: % | H38: =(1+IRR(K12:AT12))^12-1 -> 0.3567688
D40: FCFE
D41: Внутренняя ставка доходности | E41: % | H41: =(1+IRR(K15:AT15))^12-1 -> 0.3789682
D43: Шаг 4. Определите чистую приведенную стоимость
D44: FCFF
D45: Дисконтированный FCFF (NPV ~ Enterprise Value) | E45: руб | H45: =CF!H66 -> 2.4178628e+08
D47: FCFE
D48: Дисконтированный FCFE (NPV ~ Equity Value) | E48: руб | H48: =CF!H109 -> 2.2788065e+08
D51: Шаг 5. Сделайте вывод

Sheet Данные
B1: 1 Вводные данные от инициаторов проекта
B3: Дата старта проекта | C3: 47119 | E3: Плановый темп роста производства в год
B4: Продолжительность проекта | C4: 5 лет | E4: 2029 | F4: 2030 | G4: 2031 | H4: 2032 | I4: 2033
B5: Детализация модели | C5: Помесячно | E5: 0 | F5: 1.15 | G5: 0.2 | H5: 0.2 | I5: 0.2
B6: Месяц начала продаж | C6: 3 месяц
B7: Период между производством и продажей | C7: 1 месяц
B8: Рентабельность аналогичных продуктов в компании | C8: 0.45
B9: Стоимость разработки технологии | C9: 180 000 000 руб | E9: * Все инвестиции равномерно делятся на первые два месяца
B10: Маркетинг | C10: 15% от выручки
B11: АУП и непредвиденные затраты | C11: 10% от выручки
B12: Стоимость заемного финансирования | C12: 0.1
B13: Объем заемного финансирования | C13: 0.25
B14: Плановый объем производства в год запуска проекта | C14: 5 млн кг
B16: 2 Вводные данные от аналитиков
B18: Стоимость оборудования, рубли | E18: Сезонность производства молока
B19: Процессное оборудование | E19: 1 | F19: 2 | G19: 3 | H19: 4 | I19: 5 | J19: 6 | K19: 7 | L19: 8 | M19: 9 | N19: 10 | O19: 11 | P19: 12
B20: Приемка сырья | C20: 90000000 | E20: 0.75 | F20: 0.85 | G20: 0.9 | H20: 1.1 | I20: 1.2 | J20: 1.25 | K20: 1.2 | L20: 1.1 | M20: 1.05 | N20: 0.95 | O20: 0.85 | P20: 0.8
B21: Миксинг | C21: 70000000
B22: Декантация и деактивация | C22: 55000000
B23: Гомогенизация и стерилизация | C23: 90000000
B24: Упаковочная линия | E24: Прогноз инфляции
B25: Фасовка | C25: 70000000 | E25: 2029 | F25: 2030 | G25: 2031 | H25: 2032 | I25: 2033
B26: Группировка | C26: 40000000 | E26: 0.05 | F26: 0.038 | G26: 0.04 | H26: 0.04 | I26: 0.04
B27: Срок полезного использования | C27: 40 месяцев
B28: Метод расчета амортизации | C28: линейный
B30: Налоги
B31: Налог на прибыль | C31: 0.2
B32: НДС | C32: 0.2
B34: 3 Вводные данные от производственного отдела
B36: Стоимость сырья руб/кг | E36: Основные драйверы затрат
B37: Кокосовая паста | C37: 380 | E37: Число произведенных партий
B38: Карбонат кальция | C38: 75 | E38: Число переналадок оборудования
B39: Витамины | C39: 4500 | E39: Число отгруженных партий
B40: Камедь рожкового дерева | C40: 1500
B41: Лецитин подсолнечный | C41: 234
B42: Состав 1 кг продукта, кг | E42: Основные параметры производства
B43: Основа - кокосовая паста | C43: 0.17 | E43: Партия производства, кг | I43: 120
B44: Кальций | C44: 0.01 | E44: Число переналадок оборудования за партию, шт | I44: 5
B45: Витамины | C45: 0.007 | E45: Партия продажи, кг | I45: 95
B46: Стабилизатор (камедь рожкового дерева) | C46: 0.008
B47: Эмульгатор (лецитин подсолнечный) | C47: 0.005
B48: Вода | C48: 0.8
B49: Прочие прямые расходы , рубли
B50: Заработная плата производственным рабочим | C50: 20
B51: Прочие прямые затраты | C51: 5
B53: Накладные расходы за год, рубли
B54: Общие затраты по управлению цехом | C54: 4500000
B55: Затраты на наладку оборудования | C55: 4000000
B56: Административные расходы | C56: 8000000
B59: 4 Данные для расчета ставок дисконта
B61: ERP (risk market - risk free) | C61: Average ERP (Jan. 2018), Damodaran | D61: 0.0596
B62: Beta | C62: Unlevered beta for Food Processing industry (Jan. 2018), Damodaran | D62: 0.72
B64: Безрисковая ставка | C64: (Значение бескупонной доходности гос.облигаций сроком погашения 10 лет (July 2019), cbr.ru)
B65: Дата | C65: Срок до погашения, лет
B66: 0.25 | C66: 0.5 | D66: 0.75 | E66: 1 | F66: 2 | G66: 3 | H66: 5 | I66: 7 | J66: 10 | K66: 15 | L66: 20 | M66: 30
B67: 43647 | C67: 6.99 | D67: 7.01 | E67: 7.04 | F67: 7.06 | G67: 7.15 | H67: 7.22 | I67: 7.31 | J67: 7.38 | K67: 7.45 | L67: 7.54 | M67: 7.58 | N67: 7.61
B68: 43644 | C68: 6.93 | D68: 6.97 | E68: 7.01 | F68: 7.05 | G68: 7.18 | H68: 7.25 | I68: 7.35 | J68: 7.41 | K68: 7.49 | L68: 7.56 | M68: 7.59 | N68: 7.62
B69: 43643 | C69: 6.96 | D69: 7 | E69: 7.03 | F69: 7.06 | G69: 7.17 | H69: 7.25 | I69: 7.36 | J69: 7.43 | K69: 7.5 | L69: 7.58 | M69: 7.62 | N69: 7.65
B70: 43642 | C70: 6.99 | D70: 7.01 | E70: 7.04 | F70: 7.07 | G70: 7.2 | H70: 7.27 | I70: 7.36 | J70: 7.42 | K70: 7.51 | L70: 7.6 | M70: 7.65 | N70: 7.71
B71: 43641 | C71: 7.03 | D71: 7.03 | E71: 7.04 | F71: 7.06 | G71: 7.15 | H71: 7.22 | I71: 7.33 | J71: 7.41 | K71: 7.5 | L71: 7.6 | M71: 7.65 | N71: 7.71
B72: 43640 | C72: 6.99 | D72: 7 | E72: 7.03 | F72: 7.05 | G72: 7.16 | H72: 7.23 | I72: 7.32 | J72: 7.39 | K72: 7.49 | L72: 7.59 | M72: 7.65 | N72: 7.7
B73: 43637 | C73: 7 | D73: 7.02 | E73: 7.04 | F73: 7.07 | G73: 7.16 | H73: 7.24 | I73: 7.37 | J73: 7.45 | K73: 7.53 | L73: 7.62 | M73: 7.69 | N73: 7.76
B74: 43636 | C74: 7 | D74: 7.02 | E74: 7.03 | F74: 7.05 | G74: 7.14 | H74: 7.19 | I74: 7.29 | J74: 7.37 | K74: 7.44 | L74: 7.54 | M74: 7.6 | N74: 7.67
B75: 43635 | C75: 7.08 | D75: 7.07 | E75: 7.07 | F75: 7.09 | G75: 7.19 | H75: 7.27 | I75: 7.36 | J75: 7.43 | K75: 7.52 | L75: 7.62 | M75: 7.68 | N75: 7.75
B76: 43634 | C76: 7.04 | D76: 7.07 | E76: 7.1 | F76: 7.12 | G76: 7.23 | H76: 7.31 | I76: 7.44 | J76: 7.53 | K76: 7.62 | L76: 7.72 | M76: 7.78 | N76: 7.83
B77: 43633 | C77: 7.12 | D77: 7.14 | E77: 7.15 | F77: 7.17 | G77: 7.25 | H77: 7.34 | I77: 7.49 | J77: 7.59 | K77: 7.69 | L77: 7.81 | M77: 7.9 | N77: 8
B78: 43630 | C78: 7.22 | D78: 7.24 | E78: 7.25 | F78: 7.26 | G78: 7.3 | H78: 7.37 | I78: 7.5 | J78: 7.61 | K78: 7.73 | L78: 7.87 | M78: 7.97 | N78: 8.08
... B86: 43619 | C86: 7.3 | D86: 7.32 | E86: 7.34 | F86: 7.37 | G86: 7.46 | H86: 7.56 | I86: 7.73 | J86: 7.86 | K86: 8.01 | L86: 8.2 | M86: 8.32 | N86: 8.46
H88: Среднее значение | J88: =AVERAGE(J68:J86)/100 -> 0.075657895
